{
"type": "FeatureCollection",
"name": "ASHFI_8",
"crs": { "type": "name", "properties": { "name": "urn:ogc:def:crs:OGC:1.3:CRS84" } },
"features": [
{ "type": "Feature", "properties": { "osm_id": 401358690, "name": null, "amenity": "bench", "man_made": null, "leisure": null, "playground": null, "memorial": null }, "geometry": { "type": "Point", "coordinates": [ -1.2527927, 53.1223084 ] } },
{ "type": "Feature", "properties": { "osm_id": 3150342526, "name": null, "amenity": "bench", "man_made": null, "leisure": null, "playground": null, "memorial": null }, "geometry": { "type": "Point", "coordinates": [ -1.246251, 53.1243844 ] } },
{ "type": "Feature", "properties": { "osm_id": 401358638, "name": null, "amenity": "bench", "man_made": null, "leisure": null, "playground": null, "memorial": null }, "geometry": { "type": "Point", "coordinates": [ -1.2532692, 53.1236782 ] } },
{ "type": "Feature", "properties": { "osm_id": 3150375434, "name": null, "amenity": "bench", "man_made": null, "leisure": null, "playground": null, "memorial": null }, "geometry": { "type": "Point", "coordinates": [ -1.2452827, 53.1253631 ] } }
]
}
