{
"type": "FeatureCollection",
"name": "CHARN_34",
"crs": { "type": "name", "properties": { "name": "urn:ogc:def:crs:OGC:1.3:CRS84" } },
"features": [
{ "type": "Feature", "properties": { "osm_id": 12648094187, "name": null, "amenity": "bench", "man_made": null, "leisure": null, "playground": null, "memorial": null }, "geometry": { "type": "Point", "coordinates": [ -1.2237018, 52.6823231 ] } },
{ "type": "Feature", "properties": { "osm_id": 13096646447, "name": null, "amenity": "bench", "man_made": null, "leisure": null, "playground": null, "memorial": null }, "geometry": { "type": "Point", "coordinates": [ -1.2272162, 52.6839995 ] } },
{ "type": "Feature", "properties": { "osm_id": 13096646445, "name": null, "amenity": "bench", "man_made": null, "leisure": null, "playground": null, "memorial": null }, "geometry": { "type": "Point", "coordinates": [ -1.2262747, 52.684073 ] } },
{ "type": "Feature", "properties": { "osm_id": 12344369303, "name": null, "amenity": "bench", "man_made": null, "leisure": null, "playground": null, "memorial": null }, "geometry": { "type": "Point", "coordinates": [ -1.2248663, 52.6949281 ] } },
{ "type": "Feature", "properties": { "osm_id": 6237958785, "name": null, "amenity": "bench", "man_made": null, "leisure": null, "playground": null, "memorial": null }, "geometry": { "type": "Point", "coordinates": [ -1.214389, 52.685395 ] } },
{ "type": "Feature", "properties": { "osm_id": 5843701161, "name": null, "amenity": "bench", "man_made": null, "leisure": null, "playground": null, "memorial": null }, "geometry": { "type": "Point", "coordinates": [ -1.2006865, 52.6912204 ] } },
{ "type": "Feature", "properties": { "osm_id": 6249960806, "name": null, "amenity": "bench", "man_made": null, "leisure": null, "playground": null, "memorial": null }, "geometry": { "type": "Point", "coordinates": [ -1.2013614, 52.6915993 ] } },
{ "type": "Feature", "properties": { "osm_id": 5092994458, "name": null, "amenity": "bench", "man_made": null, "leisure": null, "playground": null, "memorial": null }, "geometry": { "type": "Point", "coordinates": [ -1.2126089, 52.6939063 ] } },
{ "type": "Feature", "properties": { "osm_id": 11360434392, "name": null, "amenity": "bench", "man_made": null, "leisure": null, "playground": null, "memorial": null }, "geometry": { "type": "Point", "coordinates": [ -1.2089074, 52.6977671 ] } },
{ "type": "Feature", "properties": { "osm_id": 11360434389, "name": null, "amenity": null, "man_made": null, "leisure": "picnic_table", "playground": null, "memorial": null }, "geometry": { "type": "Point", "coordinates": [ -1.2008904, 52.70015 ] } },
{ "type": "Feature", "properties": { "osm_id": 7824066012, "name": null, "amenity": "bench", "man_made": null, "leisure": null, "playground": null, "memorial": null }, "geometry": { "type": "Point", "coordinates": [ -1.2042944, 52.7051112 ] } },
{ "type": "Feature", "properties": { "osm_id": 7824066011, "name": null, "amenity": "bench", "man_made": null, "leisure": null, "playground": null, "memorial": null }, "geometry": { "type": "Point", "coordinates": [ -1.2030668, 52.7094821 ] } },
{ "type": "Feature", "properties": { "osm_id": 12828964994, "name": null, "amenity": "bench", "man_made": null, "leisure": null, "playground": null, "memorial": null }, "geometry": { "type": "Point", "coordinates": [ -1.2029775, 52.7097128 ] } },
{ "type": "Feature", "properties": { "osm_id": 10220252185, "name": null, "amenity": "bench", "man_made": null, "leisure": null, "playground": null, "memorial": null }, "geometry": { "type": "Point", "coordinates": [ -1.2250185, 52.6962138 ] } },
{ "type": "Feature", "properties": { "osm_id": 2363714896, "name": null, "amenity": "bench", "man_made": null, "leisure": null, "playground": null, "memorial": null }, "geometry": { "type": "Point", "coordinates": [ -1.2248101, 52.6972136 ] } },
{ "type": "Feature", "properties": { "osm_id": 11360434390, "name": null, "amenity": null, "man_made": null, "leisure": "picnic_table", "playground": null, "memorial": null }, "geometry": { "type": "Point", "coordinates": [ -1.224456, 52.6990866 ] } }
]
}
