{
"type": "FeatureCollection",
"name": "NOTTI_204",
"crs": { "type": "name", "properties": { "name": "urn:ogc:def:crs:OGC:1.3:CRS84" } },
"features": [
{ "type": "Feature", "properties": { "osm_id": 3511322636, "name": null, "amenity": "bench", "man_made": null, "leisure": null, "playground": null, "memorial": null }, "geometry": { "type": "Point", "coordinates": [ -1.239527, 52.9803717 ] } },
{ "type": "Feature", "properties": { "osm_id": 3511322638, "name": null, "amenity": "bench", "man_made": null, "leisure": null, "playground": null, "memorial": null }, "geometry": { "type": "Point", "coordinates": [ -1.2396165, 52.980391 ] } },
{ "type": "Feature", "properties": { "osm_id": 3511322643, "name": null, "amenity": "bench", "man_made": null, "leisure": null, "playground": null, "memorial": null }, "geometry": { "type": "Point", "coordinates": [ -1.2394335, 52.9804602 ] } },
{ "type": "Feature", "properties": { "osm_id": 3511322651, "name": null, "amenity": "bench", "man_made": null, "leisure": null, "playground": null, "memorial": null }, "geometry": { "type": "Point", "coordinates": [ -1.238919, 52.9805867 ] } },
{ "type": "Feature", "properties": { "osm_id": 3511322653, "name": null, "amenity": "bench", "man_made": null, "leisure": null, "playground": null, "memorial": null }, "geometry": { "type": "Point", "coordinates": [ -1.2388642, 52.9806129 ] } },
{ "type": "Feature", "properties": { "osm_id": 3511322655, "name": null, "amenity": "bench", "man_made": null, "leisure": null, "playground": null, "memorial": null }, "geometry": { "type": "Point", "coordinates": [ -1.2389237, 52.9806538 ] } },
{ "type": "Feature", "properties": { "osm_id": 3511322656, "name": null, "amenity": "bench", "man_made": null, "leisure": null, "playground": null, "memorial": null }, "geometry": { "type": "Point", "coordinates": [ -1.2388632, 52.9806755 ] } }
]
}
