{
"type": "FeatureCollection",
"name": "NOTTI_154",
"crs": { "type": "name", "properties": { "name": "urn:ogc:def:crs:OGC:1.3:CRS84" } },
"features": [
{ "type": "Feature", "properties": { "osm_id": 2519314629, "name": null, "amenity": "bench", "man_made": null, "leisure": null, "playground": null, "memorial": null }, "geometry": { "type": "Point", "coordinates": [ -1.1579033, 52.9496729 ] } },
{ "type": "Feature", "properties": { "osm_id": 2519314631, "name": null, "amenity": "bench", "man_made": null, "leisure": null, "playground": null, "memorial": null }, "geometry": { "type": "Point", "coordinates": [ -1.1578453, 52.9496899 ] } }
]
}
