{
"type": "FeatureCollection",
"name": "NOTTI_5",
"crs": { "type": "name", "properties": { "name": "urn:ogc:def:crs:OGC:1.3:CRS84" } },
"features": [
{ "type": "Feature", "properties": { "osm_id": 5420483783, "name": null, "amenity": "bench", "man_made": null, "leisure": null, "playground": null, "memorial": null }, "geometry": { "type": "Point", "coordinates": [ -1.1726148, 52.9495494 ] } },
{ "type": "Feature", "properties": { "osm_id": 5420483781, "name": null, "amenity": "bench", "man_made": null, "leisure": null, "playground": null, "memorial": null }, "geometry": { "type": "Point", "coordinates": [ -1.1725129, 52.9496245 ] } },
{ "type": "Feature", "properties": { "osm_id": 5420483779, "name": null, "amenity": "bench", "man_made": null, "leisure": null, "playground": null, "memorial": null }, "geometry": { "type": "Point", "coordinates": [ -1.1725384, 52.9497918 ] } },
{ "type": "Feature", "properties": { "osm_id": 5420483780, "name": null, "amenity": "bench", "man_made": null, "leisure": null, "playground": null, "memorial": null }, "geometry": { "type": "Point", "coordinates": [ -1.1726095, 52.9497942 ] } },
{ "type": "Feature", "properties": { "osm_id": 5420477615, "name": null, "amenity": "bench", "man_made": null, "leisure": null, "playground": null, "memorial": null }, "geometry": { "type": "Point", "coordinates": [ -1.1725773, 52.9498944 ] } },
{ "type": "Feature", "properties": { "osm_id": 5420477616, "name": null, "amenity": "bench", "man_made": null, "leisure": null, "playground": null, "memorial": null }, "geometry": { "type": "Point", "coordinates": [ -1.1726551, 52.9499962 ] } },
{ "type": "Feature", "properties": { "osm_id": 5420483721, "name": null, "amenity": "bench", "man_made": null, "leisure": null, "playground": null, "memorial": null }, "geometry": { "type": "Point", "coordinates": [ -1.1727959, 52.9501909 ] } }
]
}
