{
"type": "FeatureCollection",
"name": "NEWSH_28_toilets",
"crs": { "type": "name", "properties": { "name": "urn:ogc:def:crs:OGC:1.3:CRS84" } },
"features": [
{ "type": "Feature", "properties": { "name": "Unknown", "payment_info": "Free", "accessible": "False", "radar": "Unknown", "women": "Unknown", "men": "Unknown", "baby_change": "Unknown", "Mon": "Unknown", "Tue": "Unknown", "Wed": "Unknown", "Thu": "Unknown", "Fri": "Unknown", "Sat": "Unknown", "Sun": "Unknown", "index_right": 39, "park_offical_id": "NEWSH_28" }, "geometry": { "type": "Point", "coordinates": [ -1.0357906, 53.1758793 ] } },
{ "type": "Feature", "properties": { "name": "Rufford Park", "payment_info": "Free", "accessible": "Unknown", "radar": "Unknown", "women": "True", "men": "True", "baby_change": "Unknown", "Mon": "Unknown", "Tue": "Unknown", "Wed": "Unknown", "Thu": "Unknown", "Fri": "Unknown", "Sat": "Unknown", "Sun": "Unknown", "index_right": 39, "park_offical_id": "NEWSH_28" }, "geometry": { "type": "Point", "coordinates": [ -1.033057819, 53.18321795 ] } }
]
}
