{
"type": "FeatureCollection",
"name": "NEWSH_22_toilets",
"crs": { "type": "name", "properties": { "name": "urn:ogc:def:crs:OGC:1.3:CRS84" } },
"features": [
{ "type": "Feature", "properties": { "name": "macdonalds 1614 ollertonalso shell ollerton and esso ollerton", "payment_info": "Cost unknown", "accessible": "False", "radar": "Unknown", "women": "True", "men": "True", "baby_change": "Unknown", "Mon": "Unknown", "Tue": "Unknown", "Wed": "Unknown", "Thu": "Unknown", "Fri": "Unknown", "Sat": "Unknown", "Sun": "Unknown", "index_right": 32, "park_offical_id": "NEWSH_22" }, "geometry": { "type": "Point", "coordinates": [ -1.02604419, 53.20000622 ] } },
{ "type": "Feature", "properties": { "name": "Boyes Toilets", "payment_info": "000", "accessible": "True", "radar": "True", "women": "True", "men": "True", "baby_change": "True", "Mon": "Unknown", "Tue": "Unknown", "Wed": "Unknown", "Thu": "Unknown", "Fri": "Unknown", "Sat": "Unknown", "Sun": "Unknown", "index_right": 32, "park_offical_id": "NEWSH_22" }, "geometry": { "type": "Point", "coordinates": [ -1.0095191, 53.203752895 ] } }
]
}
