{
"type": "FeatureCollection",
"name": "NEWSH_37_toilets",
"crs": { "type": "name", "properties": { "name": "urn:ogc:def:crs:OGC:1.3:CRS84" } },
"features": [
{ "type": "Feature", "properties": { "name": "Vicar Water County Park visitor Centre", "payment_info": "Free", "accessible": "False", "radar": "True", "women": "True", "men": "True", "baby_change": "True", "Mon": "Unknown", "Tue": "Unknown", "Wed": "Unknown", "Thu": "Unknown", "Fri": "Unknown", "Sat": "Unknown", "Sun": "Unknown", "index_right": 49, "park_offical_id": "NEWSH_37" }, "geometry": { "type": "Point", "coordinates": [ -1.123119688, 53.160286271 ] } }
]
}
