{
"type": "FeatureCollection",
"name": "8dafa87c869d_visibility",
"crs": { "type": "name", "properties": { "name": "urn:ogc:def:crs:OGC:1.3:CRS84" } },
"features": [
{ "type": "Feature", "properties": { "visible_points": 4, "total_points": 55, "visibility_pct": 7.2727272727272725 }, "geometry": { "type": "Point", "coordinates": [ -1.944950705844814, 53.444283452467324 ] } },
{ "type": "Feature", "properties": { "visible_points": 0, "total_points": 58, "visibility_pct": 0.0 }, "geometry": { "type": "Point", "coordinates": [ -1.944742094846593, 53.444283356639986 ] } },
{ "type": "Feature", "properties": { "visible_points": 0, "total_points": 58, "visibility_pct": 0.0 }, "geometry": { "type": "Point", "coordinates": [ -1.944533483849597, 53.444283260448323 ] } },
{ "type": "Feature", "properties": { "visible_points": 7, "total_points": 48, "visibility_pct": 14.583333333333334 }, "geometry": { "type": "Point", "coordinates": [ -1.945263484990855, 53.44439145736353 ] } },
{ "type": "Feature", "properties": { "visible_points": 3, "total_points": 54, "visibility_pct": 5.5555555555555554 }, "geometry": { "type": "Point", "coordinates": [ -1.945054873458533, 53.444391362069297 ] } },
{ "type": "Feature", "properties": { "visible_points": 0, "total_points": 58, "visibility_pct": 0.0 }, "geometry": { "type": "Point", "coordinates": [ -1.94484626192743, 53.44439126641079 ] } },
{ "type": "Feature", "properties": { "visible_points": 3, "total_points": 58, "visibility_pct": 5.1724137931034484 }, "geometry": { "type": "Point", "coordinates": [ -1.944637650397549, 53.444391170387995 ] } },
{ "type": "Feature", "properties": { "visible_points": 0, "total_points": 58, "visibility_pct": 0.0 }, "geometry": { "type": "Point", "coordinates": [ -1.944429038868903, 53.444391074000897 ] } },
{ "type": "Feature", "properties": { "visible_points": 0, "total_points": 53, "visibility_pct": 0.0 }, "geometry": { "type": "Point", "coordinates": [ -1.944220427341493, 53.444390977249519 ] } },
{ "type": "Feature", "properties": { "visible_points": 7, "total_points": 52, "visibility_pct": 13.461538461538462 }, "geometry": { "type": "Point", "coordinates": [ -1.945159041603896, 53.444499271591553 ] } },
{ "type": "Feature", "properties": { "visible_points": 6, "total_points": 58, "visibility_pct": 10.344827586206897 }, "geometry": { "type": "Point", "coordinates": [ -1.944950429539908, 53.444499176101885 ] } },
{ "type": "Feature", "properties": { "visible_points": 3, "total_points": 58, "visibility_pct": 5.1724137931034484 }, "geometry": { "type": "Point", "coordinates": [ -1.944741817477146, 53.444499080247923 ] } },
{ "type": "Feature", "properties": { "visible_points": 4, "total_points": 58, "visibility_pct": 6.8965517241379306 }, "geometry": { "type": "Point", "coordinates": [ -1.944533205415611, 53.444498984029678 ] } },
{ "type": "Feature", "properties": { "visible_points": 1, "total_points": 56, "visibility_pct": 1.7857142857142856 }, "geometry": { "type": "Point", "coordinates": [ -1.94432459335531, 53.444498887447139 ] } },
{ "type": "Feature", "properties": { "visible_points": 0, "total_points": 50, "visibility_pct": 0.0 }, "geometry": { "type": "Point", "coordinates": [ -1.944115981296245, 53.444498790500312 ] } },
{ "type": "Feature", "properties": { "visible_points": 0, "total_points": 42, "visibility_pct": 0.0 }, "geometry": { "type": "Point", "coordinates": [ -1.94390736923842, 53.444498693189196 ] } },
{ "type": "Feature", "properties": { "visible_points": 5, "total_points": 55, "visibility_pct": 9.0909090909090917 }, "geometry": { "type": "Point", "coordinates": [ -1.945054597684038, 53.444607085713209 ] } },
{ "type": "Feature", "properties": { "visible_points": 5, "total_points": 58, "visibility_pct": 8.6206896551724146 }, "geometry": { "type": "Point", "coordinates": [ -1.944845985088388, 53.444606990028113 ] } },
{ "type": "Feature", "properties": { "visible_points": 6, "total_points": 58, "visibility_pct": 10.344827586206897 }, "geometry": { "type": "Point", "coordinates": [ -1.944637372493965, 53.444606893978708 ] } },
{ "type": "Feature", "properties": { "visible_points": 4, "total_points": 57, "visibility_pct": 7.0175438596491224 }, "geometry": { "type": "Point", "coordinates": [ -1.944428759900768, 53.444606797565015 ] } },
{ "type": "Feature", "properties": { "visible_points": 1, "total_points": 52, "visibility_pct": 1.9230769230769231 }, "geometry": { "type": "Point", "coordinates": [ -1.944220147308811, 53.444606700787027 ] } },
{ "type": "Feature", "properties": { "visible_points": 3, "total_points": 57, "visibility_pct": 5.2631578947368416 }, "geometry": { "type": "Point", "coordinates": [ -1.944532926977875, 53.44471470760314 ] } },
{ "type": "Feature", "properties": { "visible_points": 0, "total_points": 52, "visibility_pct": 0.0 }, "geometry": { "type": "Point", "coordinates": [ -1.944324313853021, 53.444714610994005 ] } }
]
}
