{
"type": "FeatureCollection",
"name": "2cf87b173f65_visibility",
"crs": { "type": "name", "properties": { "name": "urn:ogc:def:crs:OGC:1.3:CRS84" } },
"features": [
{ "type": "Feature", "properties": { "visible_points": 1, "total_points": 42, "visibility_pct": 2.3809523809523809 }, "geometry": { "type": "Point", "coordinates": [ -1.022617306717311, 52.862599610692698 ] } },
{ "type": "Feature", "properties": { "visible_points": 0, "total_points": 41, "visibility_pct": 0.0 }, "geometry": { "type": "Point", "coordinates": [ -1.022411524299698, 52.862597916370255 ] } },
{ "type": "Feature", "properties": { "visible_points": 0, "total_points": 39, "visibility_pct": 0.0 }, "geometry": { "type": "Point", "coordinates": [ -1.022205741902947, 52.862596221691192 ] } },
{ "type": "Feature", "properties": { "visible_points": 0, "total_points": 47, "visibility_pct": 0.0 }, "geometry": { "type": "Point", "coordinates": [ -1.0225119964287, 52.862706621092329 ] } },
{ "type": "Feature", "properties": { "visible_points": 0, "total_points": 45, "visibility_pct": 0.0 }, "geometry": { "type": "Point", "coordinates": [ -1.02230621350434, 52.862704926585259 ] } },
{ "type": "Feature", "properties": { "visible_points": 0, "total_points": 52, "visibility_pct": 0.0 }, "geometry": { "type": "Point", "coordinates": [ -1.022612469064433, 52.862815325729557 ] } },
{ "type": "Feature", "properties": { "visible_points": 0, "total_points": 51, "visibility_pct": 0.0 }, "geometry": { "type": "Point", "coordinates": [ -1.022406685612458, 52.862813631394481 ] } },
{ "type": "Feature", "properties": { "visible_points": 0, "total_points": 57, "visibility_pct": 0.0 }, "geometry": { "type": "Point", "coordinates": [ -1.022712942206894, 52.862924030281931 ] } },
{ "type": "Feature", "properties": { "visible_points": 0, "total_points": 56, "visibility_pct": 0.0 }, "geometry": { "type": "Point", "coordinates": [ -1.022507158227304, 52.862922336118807 ] } },
{ "type": "Feature", "properties": { "visible_points": 0, "total_points": 56, "visibility_pct": 0.0 }, "geometry": { "type": "Point", "coordinates": [ -1.022813415856091, 52.863032734749424 ] } },
{ "type": "Feature", "properties": { "visible_points": 0, "total_points": 57, "visibility_pct": 0.0 }, "geometry": { "type": "Point", "coordinates": [ -1.022607631348884, 52.863031040758294 ] } },
{ "type": "Feature", "properties": { "visible_points": 0, "total_points": 57, "visibility_pct": 0.0 }, "geometry": { "type": "Point", "coordinates": [ -1.022401846862537, 52.863029346410563 ] } },
{ "type": "Feature", "properties": { "visible_points": 0, "total_points": 51, "visibility_pct": 0.0 }, "geometry": { "type": "Point", "coordinates": [ -1.022913890012026, 52.863141439132065 ] } },
{ "type": "Feature", "properties": { "visible_points": 1, "total_points": 53, "visibility_pct": 1.8867924528301887 }, "geometry": { "type": "Point", "coordinates": [ -1.0227081049772, 52.863139745312921 ] } },
{ "type": "Feature", "properties": { "visible_points": 0, "total_points": 54, "visibility_pct": 0.0 }, "geometry": { "type": "Point", "coordinates": [ -1.022502319963231, 52.863138051137156 ] } },
{ "type": "Feature", "properties": { "visible_points": 0, "total_points": 48, "visibility_pct": 0.0 }, "geometry": { "type": "Point", "coordinates": [ -1.022808579112256, 52.863248449782667 ] } },
{ "type": "Feature", "properties": { "visible_points": 0, "total_points": 49, "visibility_pct": 0.0 }, "geometry": { "type": "Point", "coordinates": [ -1.022602793570666, 52.863246755778881 ] } },
{ "type": "Feature", "properties": { "visible_points": 2, "total_points": 42, "visibility_pct": 4.7619047619047619 }, "geometry": { "type": "Point", "coordinates": [ -1.022909053754061, 52.863357154167559 ] } },
{ "type": "Feature", "properties": { "visible_points": 0, "total_points": 44, "visibility_pct": 0.0 }, "geometry": { "type": "Point", "coordinates": [ -1.022703267684843, 52.863355460335761 ] } },
{ "type": "Feature", "properties": { "visible_points": 3, "total_points": 38, "visibility_pct": 7.8947368421052628 }, "geometry": { "type": "Point", "coordinates": [ -1.022803742305765, 52.863464164807745 ] } },
{ "type": "Feature", "properties": { "visible_points": 5, "total_points": 39, "visibility_pct": 12.820512820512819 }, "geometry": { "type": "Point", "coordinates": [ -1.022597955729775, 52.863462470791319 ] } }
]
}
