{
"type": "FeatureCollection",
"name": "BOLSO_14_toilets",
"crs": { "type": "name", "properties": { "name": "urn:ogc:def:crs:OGC:1.3:CRS84" } },
"features": [
{ "type": "Feature", "properties": { "name": "bolsover Castle  rear of cafe  information centre", "payment_info": "Free", "accessible": "False", "radar": "False", "women": "True", "men": "True", "baby_change": "Unknown", "Mon": "Unknown", "Tue": "Unknown", "Wed": "Unknown", "Thu": "Unknown", "Fri": "Unknown", "Sat": "Unknown", "Sun": "Unknown", "index_right": 6, "park_offical_id": "BOLSO_14" }, "geometry": { "type": "Point", "coordinates": [ -1.2941666, 53.2303005 ] } },
{ "type": "Feature", "properties": { "name": "Unknown", "payment_info": "Free", "accessible": "False", "radar": "Unknown", "women": "Unknown", "men": "Unknown", "baby_change": "Unknown", "Mon": "Unknown", "Tue": "Unknown", "Wed": "Unknown", "Thu": "Unknown", "Fri": "Unknown", "Sat": "Unknown", "Sun": "Unknown", "index_right": 6, "park_offical_id": "BOLSO_14" }, "geometry": { "type": "Point", "coordinates": [ -1.2962615, 53.230435 ] } },
{ "type": "Feature", "properties": { "name": "Old Bolsover Yard", "payment_info": "Free", "accessible": "False", "radar": "False", "women": "True", "men": "True", "baby_change": "False", "Mon": "10:00-15:00", "Tue": "10:00-15:00", "Wed": "10:00-15:00", "Thu": "10:00-15:00", "Fri": "10:00-15:00", "Sat": "10:00-15:00", "Sun": "Closed", "index_right": 6, "park_offical_id": "BOLSO_14" }, "geometry": { "type": "Point", "coordinates": [ -1.293083091, 53.22943964 ] } }
]
}
