{
"type": "FeatureCollection",
"name": "53ff3f95da07_visibility",
"crs": { "type": "name", "properties": { "name": "urn:ogc:def:crs:OGC:1.3:CRS84" } },
"features": [
{ "type": "Feature", "properties": { "visible_points": 2, "total_points": 50, "visibility_pct": 4.0 }, "geometry": { "type": "Point", "coordinates": [ -0.809939430050032, 53.209127829887294 ] } },
{ "type": "Feature", "properties": { "visible_points": 3, "total_points": 53, "visibility_pct": 5.6603773584905666 }, "geometry": { "type": "Point", "coordinates": [ -0.809732006635146, 53.209125758536999 ] } },
{ "type": "Feature", "properties": { "visible_points": 8, "total_points": 53, "visibility_pct": 15.09433962264151 }, "geometry": { "type": "Point", "coordinates": [ -0.809524583245894, 53.209123686825713 ] } },
{ "type": "Feature", "properties": { "visible_points": 0, "total_points": 54, "visibility_pct": 0.0 }, "geometry": { "type": "Point", "coordinates": [ -0.809832733154597, 53.209234637417218 ] } },
{ "type": "Feature", "properties": { "visible_points": 0, "total_points": 55, "visibility_pct": 0.0 }, "geometry": { "type": "Point", "coordinates": [ -0.809625309231999, 53.209232565877819 ] } },
{ "type": "Feature", "properties": { "visible_points": 11, "total_points": 55, "visibility_pct": 20.0 }, "geometry": { "type": "Point", "coordinates": [ -0.809417885335031, 53.209230493977422 ] } },
{ "type": "Feature", "properties": { "visible_points": 0, "total_points": 54, "visibility_pct": 0.0 }, "geometry": { "type": "Point", "coordinates": [ -0.809210461463702, 53.209228421716034 ] } },
{ "type": "Feature", "properties": { "visible_points": 9, "total_points": 55, "visibility_pct": 16.363636363636363 }, "geometry": { "type": "Point", "coordinates": [ -0.809726035725796, 53.209341444846217 ] } },
{ "type": "Feature", "properties": { "visible_points": 10, "total_points": 55, "visibility_pct": 18.181818181818183 }, "geometry": { "type": "Point", "coordinates": [ -0.809518611295482, 53.209339373117693 ] } },
{ "type": "Feature", "properties": { "visible_points": 8, "total_points": 55, "visibility_pct": 14.545454545454545 }, "geometry": { "type": "Point", "coordinates": [ -0.809311186890801, 53.209337301028157 ] } },
{ "type": "Feature", "properties": { "visible_points": 0, "total_points": 54, "visibility_pct": 0.0 }, "geometry": { "type": "Point", "coordinates": [ -0.809103762511762, 53.209335228577658 ] } },
{ "type": "Feature", "properties": { "visible_points": 2, "total_points": 55, "visibility_pct": 3.6363636363636362 }, "geometry": { "type": "Point", "coordinates": [ -0.809826762727296, 53.20945032373087 ] } },
{ "type": "Feature", "properties": { "visible_points": 10, "total_points": 55, "visibility_pct": 18.181818181818183 }, "geometry": { "type": "Point", "coordinates": [ -0.80961933776363, 53.209448252174212 ] } },
{ "type": "Feature", "properties": { "visible_points": 8, "total_points": 55, "visibility_pct": 14.545454545454545 }, "geometry": { "type": "Point", "coordinates": [ -0.809411912825596, 53.209446180256585 ] } },
{ "type": "Feature", "properties": { "visible_points": 7, "total_points": 55, "visibility_pct": 12.727272727272727 }, "geometry": { "type": "Point", "coordinates": [ -0.809204487913206, 53.209444107977959 ] } },
{ "type": "Feature", "properties": { "visible_points": 0, "total_points": 55, "visibility_pct": 0.0 }, "geometry": { "type": "Point", "coordinates": [ -0.809720064739473, 53.209557131147051 ] } },
{ "type": "Feature", "properties": { "visible_points": 11, "total_points": 55, "visibility_pct": 20.0 }, "geometry": { "type": "Point", "coordinates": [ -0.809512639268093, 53.209555059401296 ] } },
{ "type": "Feature", "properties": { "visible_points": 8, "total_points": 54, "visibility_pct": 14.814814814814813 }, "geometry": { "type": "Point", "coordinates": [ -0.809305213822339, 53.209552987294536 ] } },
{ "type": "Feature", "properties": { "visible_points": 0, "total_points": 51, "visibility_pct": 0.0 }, "geometry": { "type": "Point", "coordinates": [ -0.809097788402229, 53.209550914826771 ] } },
{ "type": "Feature", "properties": { "visible_points": 3, "total_points": 48, "visibility_pct": 6.25 }, "geometry": { "type": "Point", "coordinates": [ -0.80982079222303, 53.209666010036138 ] } },
{ "type": "Feature", "properties": { "visible_points": 10, "total_points": 50, "visibility_pct": 20.0 }, "geometry": { "type": "Point", "coordinates": [ -0.809613366218291, 53.20966393846227 ] } },
{ "type": "Feature", "properties": { "visible_points": 10, "total_points": 50, "visibility_pct": 20.0 }, "geometry": { "type": "Point", "coordinates": [ -0.809405940239176, 53.209661866527384 ] } },
{ "type": "Feature", "properties": { "visible_points": 9, "total_points": 48, "visibility_pct": 18.75 }, "geometry": { "type": "Point", "coordinates": [ -0.809198514285703, 53.209659794231513 ] } }
]
}
