{
"type": "FeatureCollection",
"name": "eaaeafcd7312_visibility",
"crs": { "type": "name", "properties": { "name": "urn:ogc:def:crs:OGC:1.3:CRS84" } },
"features": [
{ "type": "Feature", "properties": { "visible_points": 6, "total_points": 44, "visibility_pct": 13.636363636363635 }, "geometry": { "type": "Point", "coordinates": [ -0.98561310471887, 53.254077469391319 ] } },
{ "type": "Feature", "properties": { "visible_points": 8, "total_points": 50, "visibility_pct": 16.0 }, "geometry": { "type": "Point", "coordinates": [ -0.985405449536367, 53.254075704666356 ] } },
{ "type": "Feature", "properties": { "visible_points": 5, "total_points": 54, "visibility_pct": 9.2592592592592595 }, "geometry": { "type": "Point", "coordinates": [ -0.985197794375706, 53.254073939579669 ] } },
{ "type": "Feature", "properties": { "visible_points": 0, "total_points": 43, "visibility_pct": 0.0 }, "geometry": { "type": "Point", "coordinates": [ -0.985714382928122, 53.254186200017806 ] } },
{ "type": "Feature", "properties": { "visible_points": 1, "total_points": 49, "visibility_pct": 2.0408163265306123 }, "geometry": { "type": "Point", "coordinates": [ -0.985506727214747, 53.25418443546878 ] } },
{ "type": "Feature", "properties": { "visible_points": 2, "total_points": 54, "visibility_pct": 3.7037037037037033 }, "geometry": { "type": "Point", "coordinates": [ -0.985299071523209, 53.254182670558038 ] } },
{ "type": "Feature", "properties": { "visible_points": 0, "total_points": 56, "visibility_pct": 0.0 }, "geometry": { "type": "Point", "coordinates": [ -0.985091415853518, 53.254180905285573 ] } },
{ "type": "Feature", "properties": { "visible_points": 7, "total_points": 56, "visibility_pct": 12.5 }, "geometry": { "type": "Point", "coordinates": [ -0.984883760811215, 53.254179139653679 ] } },
{ "type": "Feature", "properties": { "visible_points": 7, "total_points": 50, "visibility_pct": 14.000000000000002 }, "geometry": { "type": "Point", "coordinates": [ -0.984676106893075, 53.254177373665101 ] } },
{ "type": "Feature", "properties": { "visible_points": 5, "total_points": 47, "visibility_pct": 10.638297872340425 }, "geometry": { "type": "Point", "coordinates": [ -0.985608005402144, 53.254293166183707 ] } },
{ "type": "Feature", "properties": { "visible_points": 0, "total_points": 53, "visibility_pct": 0.0 }, "geometry": { "type": "Point", "coordinates": [ -0.985400349179731, 53.254291401448903 ] } },
{ "type": "Feature", "properties": { "visible_points": 0, "total_points": 56, "visibility_pct": 0.0 }, "geometry": { "type": "Point", "coordinates": [ -0.985192692979157, 53.254289636352382 ] } },
{ "type": "Feature", "properties": { "visible_points": 0, "total_points": 56, "visibility_pct": 0.0 }, "geometry": { "type": "Point", "coordinates": [ -0.984985036933276, 53.254287870893926 ] } },
{ "type": "Feature", "properties": { "visible_points": 0, "total_points": 52, "visibility_pct": 0.0 }, "geometry": { "type": "Point", "coordinates": [ -0.984777381960947, 53.254286105077789 ] } },
{ "type": "Feature", "properties": { "visible_points": 1, "total_points": 46, "visibility_pct": 2.1739130434782608 }, "geometry": { "type": "Point", "coordinates": [ -0.98456972786271, 53.254284338901684 ] } },
{ "type": "Feature", "properties": { "visible_points": 6, "total_points": 40, "visibility_pct": 15.0 }, "geometry": { "type": "Point", "coordinates": [ -0.984362073786409, 53.25428257236392 ] } },
{ "type": "Feature", "properties": { "visible_points": 0, "total_points": 56, "visibility_pct": 0.0 }, "geometry": { "type": "Point", "coordinates": [ -0.98508631390421, 53.254396602049361 ] } },
{ "type": "Feature", "properties": { "visible_points": 0, "total_points": 53, "visibility_pct": 0.0 }, "geometry": { "type": "Point", "coordinates": [ -0.98487865784842, 53.254394836406348 ] } },
{ "type": "Feature", "properties": { "visible_points": 0, "total_points": 47, "visibility_pct": 0.0 }, "geometry": { "type": "Point", "coordinates": [ -0.984671002908636, 53.254393070402728 ] } },
{ "type": "Feature", "properties": { "visible_points": 2, "total_points": 41, "visibility_pct": 4.8780487804878048 }, "geometry": { "type": "Point", "coordinates": [ -0.984463348299023, 53.254391304038002 ] } },
{ "type": "Feature", "properties": { "visible_points": 0, "total_points": 42, "visibility_pct": 0.0 }, "geometry": { "type": "Point", "coordinates": [ -0.984564623322995, 53.254500035627402 ] } }
]
}
