{
"type": "FeatureCollection",
"name": "3055fbd9e6e9_visibility",
"crs": { "type": "name", "properties": { "name": "urn:ogc:def:crs:OGC:1.3:CRS84" } },
"features": [
{ "type": "Feature", "properties": { "visible_points": 0, "total_points": 47, "visibility_pct": 0.0 }, "geometry": { "type": "Point", "coordinates": [ -0.941518594019855, 52.240193020267142 ] } },
{ "type": "Feature", "properties": { "visible_points": 7, "total_points": 51, "visibility_pct": 13.725490196078432 }, "geometry": { "type": "Point", "coordinates": [ -0.941315709024717, 52.240191200890344 ] } },
{ "type": "Feature", "properties": { "visible_points": 4, "total_points": 48, "visibility_pct": 8.3333333333333321 }, "geometry": { "type": "Point", "coordinates": [ -0.94161747026057, 52.240301796887728 ] } },
{ "type": "Feature", "properties": { "visible_points": 0, "total_points": 53, "visibility_pct": 0.0 }, "geometry": { "type": "Point", "coordinates": [ -0.941414584767174, 52.240299977677196 ] } },
{ "type": "Feature", "properties": { "visible_points": 7, "total_points": 57, "visibility_pct": 12.280701754385964 }, "geometry": { "type": "Point", "coordinates": [ -0.941211699295237, 52.24029815811803 ] } },
{ "type": "Feature", "properties": { "visible_points": 0, "total_points": 54, "visibility_pct": 0.0 }, "geometry": { "type": "Point", "coordinates": [ -0.941513460986418, 52.240408754382834 ] } },
{ "type": "Feature", "properties": { "visible_points": 2, "total_points": 58, "visibility_pct": 3.4482758620689653 }, "geometry": { "type": "Point", "coordinates": [ -0.941310575016217, 52.240406934989956 ] } },
{ "type": "Feature", "properties": { "visible_points": 3, "total_points": 60, "visibility_pct": 5.0 }, "geometry": { "type": "Point", "coordinates": [ -0.941107689067481, 52.2404051152484 ] } },
{ "type": "Feature", "properties": { "visible_points": 0, "total_points": 53, "visibility_pct": 0.0 }, "geometry": { "type": "Point", "coordinates": [ -0.941612337682463, 52.240517531007264 ] } },
{ "type": "Feature", "properties": { "visible_points": 0, "total_points": 58, "visibility_pct": 0.0 }, "geometry": { "type": "Point", "coordinates": [ -0.941409451213993, 52.240515711780667 ] } },
{ "type": "Feature", "properties": { "visible_points": 2, "total_points": 60, "visibility_pct": 3.3333333333333335 }, "geometry": { "type": "Point", "coordinates": [ -0.941206564766984, 52.240513892205399 ] } },
{ "type": "Feature", "properties": { "visible_points": 2, "total_points": 60, "visibility_pct": 3.3333333333333335 }, "geometry": { "type": "Point", "coordinates": [ -0.941003678341444, 52.240512072281462 ] } },
{ "type": "Feature", "properties": { "visible_points": 9, "total_points": 57, "visibility_pct": 15.789473684210526 }, "geometry": { "type": "Point", "coordinates": [ -0.940800791937374, 52.240510252008903 ] } },
{ "type": "Feature", "properties": { "visible_points": 0, "total_points": 59, "visibility_pct": 0.0 }, "geometry": { "type": "Point", "coordinates": [ -0.941102554019467, 52.240620849323548 ] } },
{ "type": "Feature", "properties": { "visible_points": 0, "total_points": 56, "visibility_pct": 0.0 }, "geometry": { "type": "Point", "coordinates": [ -0.940899667117123, 52.24061902921725 ] } },
{ "type": "Feature", "properties": { "visible_points": 8, "total_points": 50, "visibility_pct": 16.0 }, "geometry": { "type": "Point", "coordinates": [ -0.940696780236249, 52.240617208762309 ] } },
{ "type": "Feature", "properties": { "visible_points": 0, "total_points": 54, "visibility_pct": 0.0 }, "geometry": { "type": "Point", "coordinates": [ -0.940998542773666, 52.240727806344395 ] } },
{ "type": "Feature", "properties": { "visible_points": 0, "total_points": 50, "visibility_pct": 0.0 }, "geometry": { "type": "Point", "coordinates": [ -0.940795655394513, 52.240725986055736 ] } },
{ "type": "Feature", "properties": { "visible_points": 0, "total_points": 43, "visibility_pct": 0.0 }, "geometry": { "type": "Point", "coordinates": [ -0.940592768036838, 52.240724165418399 ] } },
{ "type": "Feature", "properties": { "visible_points": 0, "total_points": 48, "visibility_pct": 0.0 }, "geometry": { "type": "Point", "coordinates": [ -0.940894531029573, 52.240834763267941 ] } },
{ "type": "Feature", "properties": { "visible_points": 0, "total_points": 43, "visibility_pct": 0.0 }, "geometry": { "type": "Point", "coordinates": [ -0.940691643173611, 52.240832942796892 ] } }
]
}
