{
"type": "FeatureCollection",
"name": "8abdedc1421d_visibility",
"crs": { "type": "name", "properties": { "name": "urn:ogc:def:crs:OGC:1.3:CRS84" } },
"features": [
{ "type": "Feature", "properties": { "visible_points": 0, "total_points": 48, "visibility_pct": 0.0 }, "geometry": { "type": "Point", "coordinates": [ -0.812497265070497, 52.252734498009971 ] } },
{ "type": "Feature", "properties": { "visible_points": 1, "total_points": 49, "visibility_pct": 2.0408163265306123 }, "geometry": { "type": "Point", "coordinates": [ -0.812294326183859, 52.252732454573845 ] } },
{ "type": "Feature", "properties": { "visible_points": 10, "total_points": 52, "visibility_pct": 19.230769230769234 }, "geometry": { "type": "Point", "coordinates": [ -0.812595855400258, 52.252843381595149 ] } },
{ "type": "Feature", "properties": { "visible_points": 2, "total_points": 53, "visibility_pct": 3.7735849056603774 }, "geometry": { "type": "Point", "coordinates": [ -0.812392916008868, 52.252841338326107 ] } },
{ "type": "Feature", "properties": { "visible_points": 0, "total_points": 54, "visibility_pct": 0.0 }, "geometry": { "type": "Point", "coordinates": [ -0.812189976641744, 52.252839294708238 ] } },
{ "type": "Feature", "properties": { "visible_points": 8, "total_points": 55, "visibility_pct": 14.545454545454545 }, "geometry": { "type": "Point", "coordinates": [ -0.812694446210486, 52.252952265098401 ] } },
{ "type": "Feature", "properties": { "visible_points": 7, "total_points": 57, "visibility_pct": 12.280701754385964 }, "geometry": { "type": "Point", "coordinates": [ -0.81249150631434, 52.252950221996421 ] } },
{ "type": "Feature", "properties": { "visible_points": 0, "total_points": 58, "visibility_pct": 0.0 }, "geometry": { "type": "Point", "coordinates": [ -0.812288566442466, 52.252948178545623 ] } },
{ "type": "Feature", "properties": { "visible_points": 0, "total_points": 58, "visibility_pct": 0.0 }, "geometry": { "type": "Point", "coordinates": [ -0.812085626594863, 52.252946134746018 ] } },
{ "type": "Feature", "properties": { "visible_points": 10, "total_points": 58, "visibility_pct": 17.241379310344829 }, "geometry": { "type": "Point", "coordinates": [ -0.812590097100292, 52.253059105584803 ] } },
{ "type": "Feature", "properties": { "visible_points": 3, "total_points": 58, "visibility_pct": 5.1724137931034484 }, "geometry": { "type": "Point", "coordinates": [ -0.812387156723658, 52.253057062301089 ] } },
{ "type": "Feature", "properties": { "visible_points": 0, "total_points": 58, "visibility_pct": 0.0 }, "geometry": { "type": "Point", "coordinates": [ -0.812184216371297, 52.253055018668547 ] } },
{ "type": "Feature", "properties": { "visible_points": 0, "total_points": 58, "visibility_pct": 0.0 }, "geometry": { "type": "Point", "coordinates": [ -0.811981276043215, 52.253052974687179 ] } },
{ "type": "Feature", "properties": { "visible_points": 9, "total_points": 58, "visibility_pct": 15.517241379310345 }, "geometry": { "type": "Point", "coordinates": [ -0.812485747485325, 52.253165945974601 ] } },
{ "type": "Feature", "properties": { "visible_points": 1, "total_points": 58, "visibility_pct": 1.7241379310344827 }, "geometry": { "type": "Point", "coordinates": [ -0.812282806628206, 52.253163902509144 ] } },
{ "type": "Feature", "properties": { "visible_points": 0, "total_points": 57, "visibility_pct": 0.0 }, "geometry": { "type": "Point", "coordinates": [ -0.812079865795359, 52.253161858694838 ] } },
{ "type": "Feature", "properties": { "visible_points": 2, "total_points": 54, "visibility_pct": 3.7037037037037033 }, "geometry": { "type": "Point", "coordinates": [ -0.811876924986787, 52.25315981453172 ] } },
{ "type": "Feature", "properties": { "visible_points": 9, "total_points": 55, "visibility_pct": 16.363636363636363 }, "geometry": { "type": "Point", "coordinates": [ -0.81238139736559, 52.253272786267779 ] } },
{ "type": "Feature", "properties": { "visible_points": 6, "total_points": 54, "visibility_pct": 11.111111111111111 }, "geometry": { "type": "Point", "coordinates": [ -0.812178456027978, 52.253270742620558 ] } },
{ "type": "Feature", "properties": { "visible_points": 0, "total_points": 52, "visibility_pct": 0.0 }, "geometry": { "type": "Point", "coordinates": [ -0.811975514714645, 52.253268698624517 ] } },
{ "type": "Feature", "properties": { "visible_points": 7, "total_points": 50, "visibility_pct": 14.000000000000002 }, "geometry": { "type": "Point", "coordinates": [ -0.812277046741078, 52.253379626464344 ] } },
{ "type": "Feature", "properties": { "visible_points": 0, "total_points": 49, "visibility_pct": 0.0 }, "geometry": { "type": "Point", "coordinates": [ -0.81207410492297, 52.25337758263538 ] } },
{ "type": "Feature", "properties": { "visible_points": 2, "total_points": 44, "visibility_pct": 4.5454545454545459 }, "geometry": { "type": "Point", "coordinates": [ -0.812172695611781, 52.25348646656429 ] } }
]
}
