{
"type": "FeatureCollection",
"name": "f7660c610f99_visibility",
"crs": { "type": "name", "properties": { "name": "urn:ogc:def:crs:OGC:1.3:CRS84" } },
"features": [
{ "type": "Feature", "properties": { "visible_points": 13, "total_points": 55, "visibility_pct": 23.636363636363637 }, "geometry": { "type": "Point", "coordinates": [ -1.176819056310114, 52.26484755871666 ] } },
{ "type": "Feature", "properties": { "visible_points": 0, "total_points": 52, "visibility_pct": 0.0 }, "geometry": { "type": "Point", "coordinates": [ -1.176616038740306, 52.264846142933806 ] } },
{ "type": "Feature", "properties": { "visible_points": 11, "total_points": 55, "visibility_pct": 20.0 }, "geometry": { "type": "Point", "coordinates": [ -1.177121585864542, 52.264957556094863 ] } },
{ "type": "Feature", "properties": { "visible_points": 18, "total_points": 55, "visibility_pct": 32.727272727272727 }, "geometry": { "type": "Point", "coordinates": [ -1.176918567745671, 52.264956140800408 ] } },
{ "type": "Feature", "properties": { "visible_points": 9, "total_points": 55, "visibility_pct": 16.363636363636363 }, "geometry": { "type": "Point", "coordinates": [ -1.176715549644421, 52.264954725157629 ] } },
{ "type": "Feature", "properties": { "visible_points": 2, "total_points": 53, "visibility_pct": 3.7735849056603774 }, "geometry": { "type": "Point", "coordinates": [ -1.176512531560787, 52.264953309166557 ] } },
{ "type": "Feature", "properties": { "visible_points": 5, "total_points": 47, "visibility_pct": 10.638297872340425 }, "geometry": { "type": "Point", "coordinates": [ -1.176309513494781, 52.264951892827156 ] } },
{ "type": "Feature", "properties": { "visible_points": 0, "total_points": 55, "visibility_pct": 0.0 }, "geometry": { "type": "Point", "coordinates": [ -1.177221098345371, 52.265066137982934 ] } },
{ "type": "Feature", "properties": { "visible_points": 5, "total_points": 55, "visibility_pct": 9.0909090909090917 }, "geometry": { "type": "Point", "coordinates": [ -1.177018079695049, 52.265064722828569 ] } },
{ "type": "Feature", "properties": { "visible_points": 10, "total_points": 55, "visibility_pct": 18.181818181818183 }, "geometry": { "type": "Point", "coordinates": [ -1.176815061062351, 52.265063307325853 ] } },
{ "type": "Feature", "properties": { "visible_points": 0, "total_points": 55, "visibility_pct": 0.0 }, "geometry": { "type": "Point", "coordinates": [ -1.176612042447263, 52.265061891474865 ] } },
{ "type": "Feature", "properties": { "visible_points": 3, "total_points": 52, "visibility_pct": 5.7692307692307692 }, "geometry": { "type": "Point", "coordinates": [ -1.176409023849808, 52.265060475275568 ] } },
{ "type": "Feature", "properties": { "visible_points": 2, "total_points": 46, "visibility_pct": 4.3478260869565215 }, "geometry": { "type": "Point", "coordinates": [ -1.176206005269971, 52.265059058727942 ] } },
{ "type": "Feature", "properties": { "visible_points": 3, "total_points": 51, "visibility_pct": 5.8823529411764701 }, "geometry": { "type": "Point", "coordinates": [ -1.177320611340028, 52.265174719815391 ] } },
{ "type": "Feature", "properties": { "visible_points": 3, "total_points": 55, "visibility_pct": 5.4545454545454541 }, "geometry": { "type": "Point", "coordinates": [ -1.177117592158256, 52.265173304801095 ] } },
{ "type": "Feature", "properties": { "visible_points": 7, "total_points": 55, "visibility_pct": 12.727272727272727 }, "geometry": { "type": "Point", "coordinates": [ -1.176914572994104, 52.265171889438491 ] } },
{ "type": "Feature", "properties": { "visible_points": 6, "total_points": 55, "visibility_pct": 10.909090909090908 }, "geometry": { "type": "Point", "coordinates": [ -1.176711553847565, 52.265170473727565 ] } },
{ "type": "Feature", "properties": { "visible_points": 1, "total_points": 55, "visibility_pct": 1.8181818181818181 }, "geometry": { "type": "Point", "coordinates": [ -1.17650853471865, 52.265169057668345 ] } },
{ "type": "Feature", "properties": { "visible_points": 2, "total_points": 51, "visibility_pct": 3.9215686274509802 }, "geometry": { "type": "Point", "coordinates": [ -1.17721710513529, 52.265281886718036 ] } },
{ "type": "Feature", "properties": { "visible_points": 7, "total_points": 55, "visibility_pct": 12.727272727272727 }, "geometry": { "type": "Point", "coordinates": [ -1.177014085439684, 52.265280471495522 ] } },
{ "type": "Feature", "properties": { "visible_points": 7, "total_points": 55, "visibility_pct": 12.727272727272727 }, "geometry": { "type": "Point", "coordinates": [ -1.17681106576169, 52.265279055924694 ] } },
{ "type": "Feature", "properties": { "visible_points": 8, "total_points": 52, "visibility_pct": 15.384615384615385 }, "geometry": { "type": "Point", "coordinates": [ -1.176910578189643, 52.265387638066201 ] } }
]
}
