{
"type": "FeatureCollection",
"name": "MANSF_33_toilets",
"crs": { "type": "name", "properties": { "name": "urn:ogc:def:crs:OGC:1.3:CRS84" } },
"features": [
{ "type": "Feature", "properties": { "name": "Morrisons", "payment_info": "Cost unknown", "accessible": "True", "radar": "False", "women": "True", "men": "True", "baby_change": "True", "Mon": "09:00-17:00", "Tue": "09:00-17:00", "Wed": "09:00-17:00", "Thu": "09:00-17:00", "Fri": "09:00-17:00", "Sat": "09:00-17:00", "Sun": "09:00-17:00", "index_right": 27, "park_offical_id": "MANSF_33" }, "geometry": { "type": "Point", "coordinates": [ -1.229556799, 53.135662805 ] } },
{ "type": "Feature", "properties": { "name": "KMHospital", "payment_info": "Cost unknown", "accessible": "True", "radar": "False", "women": "True", "men": "True", "baby_change": "True", "Mon": "00:00-00:00", "Tue": "00:00-00:00", "Wed": "00:00-00:00", "Thu": "00:00-00:00", "Fri": "00:00-00:00", "Sat": "00:00-00:00", "Sun": "00:00-00:00", "index_right": 27, "park_offical_id": "MANSF_33" }, "geometry": { "type": "Point", "coordinates": [ -1.234717369, 53.135533693 ] } },
{ "type": "Feature", "properties": { "name": "Costa Coffee", "payment_info": "Cost unknown", "accessible": "True", "radar": "False", "women": "True", "men": "True", "baby_change": "True", "Mon": "09:00-17:00", "Tue": "09:00-17:00", "Wed": "09:00-17:00", "Thu": "09:00-17:00", "Fri": "09:00-17:00", "Sat": "09:00-17:00", "Sun": "09:00-17:00", "index_right": 27, "park_offical_id": "MANSF_33" }, "geometry": { "type": "Point", "coordinates": [ -1.221177578, 53.135417859 ] } }
]
}
