{
"type": "FeatureCollection",
"name": "DERBY_47_toilets",
"crs": { "type": "name", "properties": { "name": "urn:ogc:def:crs:OGC:1.3:CRS84" } },
"features": [
{ "type": "Feature", "properties": { "name": "Cavendish toilet", "payment_info": "Cost unknown", "accessible": "False", "radar": "False", "women": "Unknown", "men": "Unknown", "baby_change": "False", "Mon": "09:00-17:00", "Tue": "09:00-17:00", "Wed": "09:00-17:00", "Thu": "09:00-17:00", "Fri": "09:00-17:00", "Sat": "09:00-17:00", "Sun": "09:00-17:00", "index_right": 60, "park_offical_id": "DERBY_47" }, "geometry": { "type": "Point", "coordinates": [ -1.485493183, 52.901868163 ] } },
{ "type": "Feature", "properties": { "name": "Arboretum", "payment_info": "Cost unknown", "accessible": "False", "radar": "True", "women": "True", "men": "True", "baby_change": "False", "Mon": "13:00-19:00", "Tue": "13:00-19:00", "Wed": "13:00-19:00", "Thu": "13:00-19:00", "Fri": "13:00-19:00", "Sat": "Closed", "Sun": "Closed", "index_right": 60, "park_offical_id": "DERBY_47" }, "geometry": { "type": "Point", "coordinates": [ -1.474993468, 52.91335565 ] } }
]
}
