{
"type": "FeatureCollection",
"name": "DERBY_11_toilets",
"crs": { "type": "name", "properties": { "name": "urn:ogc:def:crs:OGC:1.3:CRS84" } },
"features": [
{ "type": "Feature", "properties": { "name": "Unknown", "payment_info": "Cost unknown", "accessible": "False", "radar": "Unknown", "women": "True", "men": "True", "baby_change": "False", "Mon": "08:00-17:00", "Tue": "08:00-17:00", "Wed": "08:00-17:00", "Thu": "08:00-17:00", "Fri": "08:00-17:00", "Sat": "08:00-17:00", "Sun": "08:00-17:00", "index_right": 11, "park_offical_id": "DERBY_11" }, "geometry": { "type": "Point", "coordinates": [ -1.504628174, 52.92195825 ] } }
]
}
