{
"type": "FeatureCollection",
"name": "NORE5_43_toilets",
"crs": { "type": "name", "properties": { "name": "urn:ogc:def:crs:OGC:1.3:CRS84" } },
"features": [
{ "type": "Feature", "properties": { "name": "Cliffe Park", "payment_info": "Free", "accessible": "False", "radar": "Unknown", "women": "True", "men": "True", "baby_change": "True", "Mon": "09:00-18:00", "Tue": "09:00-18:00", "Wed": "09:00-18:00", "Thu": "09:00-18:00", "Fri": "09:00-18:00", "Sat": "09:00-18:00", "Sun": "09:00-18:00", "index_right": 58, "park_offical_id": "NORE5_43" }, "geometry": { "type": "Point", "coordinates": [ -1.464298368, 53.301457066 ] } },
{ "type": "Feature", "properties": { "name": "Dronfield The Forge shopping centre ", "payment_info": "Free", "accessible": "Unknown", "radar": "Unknown", "women": "True", "men": "True", "baby_change": "Unknown", "Mon": "Unknown", "Tue": "Unknown", "Wed": "Unknown", "Thu": "Unknown", "Fri": "Unknown", "Sat": "Unknown", "Sun": "Unknown", "index_right": 58, "park_offical_id": "NORE5_43" }, "geometry": { "type": "Point", "coordinates": [ -1.470751762, 53.301287158 ] } }
]
}
