{
"type": "FeatureCollection",
"name": "HINBO_58_toilets",
"crs": { "type": "name", "properties": { "name": "urn:ogc:def:crs:OGC:1.3:CRS84" } },
"features": [
{ "type": "Feature", "properties": { "name": "Barwell", "payment_info": "nil", "accessible": "True", "radar": "True", "women": "True", "men": "True", "baby_change": "False", "Mon": "09:00-18:00", "Tue": "09:00-18:00", "Wed": "09:00-18:00", "Thu": "09:00-18:00", "Fri": "09:00-18:00", "Sat": "09:00-18:00", "Sun": "09:00-18:00", "index_right": 47, "park_offical_id": "HINBO_58" }, "geometry": { "type": "Point", "coordinates": [ -1.345605254, 52.567703627 ] } }
]
}
