{
"type": "FeatureCollection",
"name": "36bbba0346ea_visibility",
"crs": { "type": "name", "properties": { "name": "urn:ogc:def:crs:OGC:1.3:CRS84" } },
"features": [
{ "type": "Feature", "properties": { "visible_points": 1, "total_points": 37, "visibility_pct": 2.7027027027027026 }, "geometry": { "type": "Point", "coordinates": [ -1.568396003123527, 53.082203505221763 ] } },
{ "type": "Feature", "properties": { "visible_points": 2, "total_points": 36, "visibility_pct": 5.5555555555555554 }, "geometry": { "type": "Point", "coordinates": [ -1.568189151018283, 53.082202755810243 ] } },
{ "type": "Feature", "properties": { "visible_points": 0, "total_points": 42, "visibility_pct": 0.0 }, "geometry": { "type": "Point", "coordinates": [ -1.568291498973455, 53.082310996069445 ] } },
{ "type": "Feature", "properties": { "visible_points": 0, "total_points": 41, "visibility_pct": 0.0 }, "geometry": { "type": "Point", "coordinates": [ -1.568084646299561, 53.082310246455208 ] } },
{ "type": "Feature", "properties": { "visible_points": 0, "total_points": 47, "visibility_pct": 0.0 }, "geometry": { "type": "Point", "coordinates": [ -1.568393847412913, 53.082419236233363 ] } },
{ "type": "Feature", "properties": { "visible_points": 0, "total_points": 46, "visibility_pct": 0.0 }, "geometry": { "type": "Point", "coordinates": [ -1.56818699426214, 53.082418486817453 ] } },
{ "type": "Feature", "properties": { "visible_points": 0, "total_points": 51, "visibility_pct": 0.0 }, "geometry": { "type": "Point", "coordinates": [ -1.568289342725656, 53.082526727074999 ] } },
{ "type": "Feature", "properties": { "visible_points": 0, "total_points": 50, "visibility_pct": 0.0 }, "geometry": { "type": "Point", "coordinates": [ -1.568082489008586, 53.082525977456037 ] } },
{ "type": "Feature", "properties": { "visible_points": 0, "total_points": 54, "visibility_pct": 0.0 }, "geometry": { "type": "Point", "coordinates": [ -1.56839169167426, 53.082634967237091 ] } },
{ "type": "Feature", "properties": { "visible_points": 0, "total_points": 54, "visibility_pct": 0.0 }, "geometry": { "type": "Point", "coordinates": [ -1.568184837478041, 53.08263421781681 ] } },
{ "type": "Feature", "properties": { "visible_points": 2, "total_points": 50, "visibility_pct": 4.0 }, "geometry": { "type": "Point", "coordinates": [ -1.568494041141363, 53.082743207309449 ] } },
{ "type": "Feature", "properties": { "visible_points": 0, "total_points": 51, "visibility_pct": 0.0 }, "geometry": { "type": "Point", "coordinates": [ -1.568287186449819, 53.082742458072651 ] } },
{ "type": "Feature", "properties": { "visible_points": 1, "total_points": 51, "visibility_pct": 1.9607843137254901 }, "geometry": { "type": "Point", "coordinates": [ -1.568080331689666, 53.082741708449007 ] } },
{ "type": "Feature", "properties": { "visible_points": 0, "total_points": 47, "visibility_pct": 0.0 }, "geometry": { "type": "Point", "coordinates": [ -1.568389535907577, 53.082850698232946 ] } },
{ "type": "Feature", "properties": { "visible_points": 0, "total_points": 47, "visibility_pct": 0.0 }, "geometry": { "type": "Point", "coordinates": [ -1.568182680665981, 53.082849948808281 ] } },
{ "type": "Feature", "properties": { "visible_points": 1, "total_points": 42, "visibility_pct": 2.3809523809523809 }, "geometry": { "type": "Point", "coordinates": [ -1.568491885883845, 53.082958938303506 ] } },
{ "type": "Feature", "properties": { "visible_points": 0, "total_points": 43, "visibility_pct": 0.0 }, "geometry": { "type": "Point", "coordinates": [ -1.568285030145937, 53.082958189062467 ] } },
{ "type": "Feature", "properties": { "visible_points": 1, "total_points": 43, "visibility_pct": 2.3255813953488373 }, "geometry": { "type": "Point", "coordinates": [ -1.568078174342803, 53.08295743943409 ] } },
{ "type": "Feature", "properties": { "visible_points": 0, "total_points": 38, "visibility_pct": 0.0 }, "geometry": { "type": "Point", "coordinates": [ -1.568594236378615, 53.08306717828431 ] } },
{ "type": "Feature", "properties": { "visible_points": 0, "total_points": 39, "visibility_pct": 0.0 }, "geometry": { "type": "Point", "coordinates": [ -1.568387380112862, 53.083066429220935 ] } },
{ "type": "Feature", "properties": { "visible_points": 1, "total_points": 39, "visibility_pct": 2.5641025641025639 }, "geometry": { "type": "Point", "coordinates": [ -1.568180523825958, 53.0830656797919 ] } },
{ "type": "Feature", "properties": { "visible_points": 0, "total_points": 34, "visibility_pct": 0.0 }, "geometry": { "type": "Point", "coordinates": [ -1.568489730598293, 53.083174669289676 ] } }
]
}
