{
"type": "FeatureCollection",
"name": "High Peak_street_lamps",
"crs": { "type": "name", "properties": { "name": "urn:ogc:def:crs:OGC:1.3:CRS84" } },
"features": [
{ "type": "Feature", "properties": { "element_type": "node", "osmid": 6721918772, "authority": "High Peak", "source": "osm", "year": null }, "geometry": { "type": "Point", "coordinates": [ -1.9945094, 53.3264246 ] } },
{ "type": "Feature", "properties": { "element_type": "node", "osmid": 6721918783, "authority": "High Peak", "source": "osm", "year": null }, "geometry": { "type": "Point", "coordinates": [ -1.9913531, 53.3274967 ] } },
{ "type": "Feature", "properties": { "element_type": "node", "osmid": 13140545414, "authority": "High Peak", "source": "osm", "year": null }, "geometry": { "type": "Point", "coordinates": [ -1.928018, 53.245652 ] } }
]
}
