{
"type": "FeatureCollection",
"name": "EASLI_82",
"crs": { "type": "name", "properties": { "name": "urn:ogc:def:crs:OGC:1.3:CRS84" } },
"features": [
{ "type": "Feature", "properties": { "osm_id": 5031846007, "name": "Martin Robertson memorial bench", "amenity": "bench", "man_made": null, "leisure": null, "playground": null, "memorial": null }, "geometry": { "type": "Point", "coordinates": [ 0.2828631, 53.313782 ] } },
{ "type": "Feature", "properties": { "osm_id": 5031846005, "name": null, "amenity": null, "man_made": null, "leisure": "picnic_table", "playground": null, "memorial": null }, "geometry": { "type": "Point", "coordinates": [ 0.2828804, 53.3138292 ] } },
{ "type": "Feature", "properties": { "osm_id": 5031846004, "name": null, "amenity": "bench", "man_made": null, "leisure": null, "playground": null, "memorial": null }, "geometry": { "type": "Point", "coordinates": [ 0.2829751, 53.3138307 ] } }
]
}
