{
"type": "FeatureCollection",
"name": "WESNO_88_toilets",
"crs": { "type": "name", "properties": { "name": "urn:ogc:def:crs:OGC:1.3:CRS84" } },
"features": [
{ "type": "Feature", "properties": { "name": "Asda", "payment_info": "Free", "accessible": "True", "radar": "Unknown", "women": "True", "men": "True", "baby_change": "Unknown", "Mon": "09:00-17:00", "Tue": "09:00-17:00", "Wed": "09:00-17:00", "Thu": "09:00-17:00", "Fri": "09:00-17:00", "Sat": "09:00-17:00", "Sun": "09:00-17:00", "index_right": 614, "park_offical_id": "WESNO_88" }, "geometry": { "type": "Point", "coordinates": [ -0.901523899, 52.261847559 ] } },
{ "type": "Feature", "properties": { "name": "Waitrose", "payment_info": "Free", "accessible": "True", "radar": "Unknown", "women": "True", "men": "True", "baby_change": "Unknown", "Mon": "09:00-17:00", "Tue": "09:00-17:00", "Wed": "09:00-17:00", "Thu": "09:00-17:00", "Fri": "09:00-17:00", "Sat": "09:00-17:00", "Sun": "09:00-17:00", "index_right": 614, "park_offical_id": "WESNO_88" }, "geometry": { "type": "Point", "coordinates": [ -0.901200771, 52.262595885 ] } },
{ "type": "Feature", "properties": { "name": "Aldi", "payment_info": "Free", "accessible": "True", "radar": "Unknown", "women": "True", "men": "True", "baby_change": "Unknown", "Mon": "09:00-17:00", "Tue": "09:00-17:00", "Wed": "09:00-17:00", "Thu": "09:00-17:00", "Fri": "09:00-17:00", "Sat": "09:00-17:00", "Sun": "09:00-17:00", "index_right": 614, "park_offical_id": "WESNO_88" }, "geometry": { "type": "Point", "coordinates": [ -0.901533365, 52.255838428 ] } }
]
}
