{
"type": "FeatureCollection",
"name": "WESNO_443_toilets",
"crs": { "type": "name", "properties": { "name": "urn:ogc:def:crs:OGC:1.3:CRS84" } },
"features": [
{ "type": "Feature", "properties": { "name": "Unknown", "payment_info": "20p", "accessible": "True", "radar": "Unknown", "women": "Unknown", "men": "Unknown", "baby_change": "Unknown", "Mon": "00:00-00:00", "Tue": "00:00-00:00", "Wed": "00:00-00:00", "Thu": "00:00-00:00", "Fri": "00:00-00:00", "Sat": "00:00-00:00", "Sun": "00:00-00:00", "index_right": 328, "park_offical_id": "WESNO_443" }, "geometry": { "type": "Point", "coordinates": [ -0.8948318, 52.2378293 ] } }
]
}
