{
"type": "FeatureCollection",
"name": "WESNO_98_toilets",
"crs": { "type": "name", "properties": { "name": "urn:ogc:def:crs:OGC:1.3:CRS84" } },
"features": [
{ "type": "Feature", "properties": { "name": "Grosvenor Centre", "payment_info": "Free", "accessible": "True", "radar": "True", "women": "True", "men": "True", "baby_change": "True", "Mon": "09:00-17:00", "Tue": "09:00-17:00", "Wed": "09:00-17:00", "Thu": "09:00-17:00", "Fri": "09:00-17:00", "Sat": "09:00-17:00", "Sun": "09:00-17:00", "index_right": 636, "park_offical_id": "WESNO_98" }, "geometry": { "type": "Point", "coordinates": [ -0.894194841, 52.23863313 ] } },
{ "type": "Feature", "properties": { "name": "Unknown", "payment_info": "20p", "accessible": "True", "radar": "Unknown", "women": "Unknown", "men": "Unknown", "baby_change": "Unknown", "Mon": "00:00-00:00", "Tue": "00:00-00:00", "Wed": "00:00-00:00", "Thu": "00:00-00:00", "Fri": "00:00-00:00", "Sat": "00:00-00:00", "Sun": "00:00-00:00", "index_right": 636, "park_offical_id": "WESNO_98" }, "geometry": { "type": "Point", "coordinates": [ -0.8948318, 52.2378293 ] } }
]
}
