{
"type": "FeatureCollection",
"name": "BASSE_32",
"crs": { "type": "name", "properties": { "name": "urn:ogc:def:crs:OGC:1.3:CRS84" } },
"features": [
{ "type": "Feature", "properties": { "osm_id": 11522087068, "name": null, "amenity": "bench", "man_made": null, "leisure": null, "playground": null, "memorial": null }, "geometry": { "type": "Point", "coordinates": [ -1.1292715, 53.371342 ] } },
{ "type": "Feature", "properties": { "osm_id": 11522087037, "name": null, "amenity": null, "man_made": null, "leisure": "picnic_table", "playground": null, "memorial": null }, "geometry": { "type": "Point", "coordinates": [ -1.1290068, 53.3725333 ] } },
{ "type": "Feature", "properties": { "osm_id": 11522087028, "name": null, "amenity": null, "man_made": null, "leisure": "picnic_table", "playground": null, "memorial": null }, "geometry": { "type": "Point", "coordinates": [ -1.1290022, 53.3725819 ] } }
]
}
