{
"type": "FeatureCollection",
"name": "OADWI_7_toilets",
"crs": { "type": "name", "properties": { "name": "urn:ogc:def:crs:OGC:1.3:CRS84" } },
"features": [
{ "type": "Feature", "properties": { "name": "Car Park East Street Oadby", "payment_info": "Free", "accessible": "False", "radar": "False", "women": "Unknown", "men": "Unknown", "baby_change": "Unknown", "Mon": "00:00-00:00", "Tue": "00:00-00:00", "Wed": "00:00-00:00", "Thu": "00:00-00:00", "Fri": "00:00-00:00", "Sat": "00:00-00:00", "Sun": "00:00-00:00", "index_right": 25, "park_offical_id": "OADWI_7" }, "geometry": { "type": "Point", "coordinates": [ -1.083043814, 52.600354721 ] } },
{ "type": "Feature", "properties": { "name": "SHELL London Road", "payment_info": "Free", "accessible": "True", "radar": "False", "women": "True", "men": "True", "baby_change": "Unknown", "Mon": "09:00-17:00", "Tue": "09:00-17:00", "Wed": "09:00-17:00", "Thu": "09:00-17:00", "Fri": "09:00-17:00", "Sat": "Closed", "Sun": "Closed", "index_right": 25, "park_offical_id": "OADWI_7" }, "geometry": { "type": "Point", "coordinates": [ -1.095435619, 52.607007443 ] } }
]
}
