{
"type": "FeatureCollection",
"name": "CHEST_64_toilets",
"crs": { "type": "name", "properties": { "name": "urn:ogc:def:crs:OGC:1.3:CRS84" } },
"features": [
{ "type": "Feature", "properties": { "name": "Poolsbrook Country Park off Fan Rd", "payment_info": "Cost unknown", "accessible": "False", "radar": "True", "women": "True", "men": "True", "baby_change": "False", "Mon": "Unknown", "Tue": "Unknown", "Wed": "Unknown", "Thu": "Unknown", "Fri": "Unknown", "Sat": "Unknown", "Sun": "Unknown", "index_right": 52, "park_offical_id": "CHEST_64" }, "geometry": { "type": "Point", "coordinates": [ -1.349412527, 53.257829643 ] } }
]
}
