{
"type": "FeatureCollection",
"name": "LINCO_16_toilets",
"crs": { "type": "name", "properties": { "name": "urn:ogc:def:crs:OGC:1.3:CRS84" } },
"features": [
{ "type": "Feature", "properties": { "name": "The Lawn Visitors Centre", "payment_info": "Free", "accessible": "False", "radar": "Unknown", "women": "True", "men": "True", "baby_change": "True", "Mon": "Unknown", "Tue": "Unknown", "Wed": "Unknown", "Thu": "Unknown", "Fri": "Unknown", "Sat": "Unknown", "Sun": "Unknown", "index_right": 13, "park_offical_id": "LINCO_16" }, "geometry": { "type": "Point", "coordinates": [ -0.544293251, 53.235122859 ] } }
]
}
