{
"type": "FeatureCollection",
"name": "LINCO_11_toilets",
"crs": { "type": "name", "properties": { "name": "urn:ogc:def:crs:OGC:1.3:CRS84" } },
"features": [
{ "type": "Feature", "properties": { "name": "Castle Square", "payment_info": "020", "accessible": "True", "radar": "True", "women": "True", "men": "True", "baby_change": "True", "Mon": "09:00-17:00", "Tue": "09:00-17:00", "Wed": "09:00-17:00", "Thu": "09:00-17:00", "Fri": "09:00-17:00", "Sat": "09:00-17:00", "Sun": "09:00-17:00", "index_right": 5, "park_offical_id": "LINCO_11" }, "geometry": { "type": "Point", "coordinates": [ -0.539464653, 53.234294069 ] } },
{ "type": "Feature", "properties": { "name": "The Lawn Visitors Centre", "payment_info": "Free", "accessible": "False", "radar": "Unknown", "women": "True", "men": "True", "baby_change": "True", "Mon": "Unknown", "Tue": "Unknown", "Wed": "Unknown", "Thu": "Unknown", "Fri": "Unknown", "Sat": "Unknown", "Sun": "Unknown", "index_right": 5, "park_offical_id": "LINCO_11" }, "geometry": { "type": "Point", "coordinates": [ -0.544293251, 53.235122859 ] } },
{ "type": "Feature", "properties": { "name": "Lincoln Cathedral Visitor Centre", "payment_info": "Free", "accessible": "Unknown", "radar": "Unknown", "women": "True", "men": "True", "baby_change": "Unknown", "Mon": "Unknown", "Tue": "Unknown", "Wed": "Unknown", "Thu": "Unknown", "Fri": "Unknown", "Sat": "Unknown", "Sun": "Unknown", "index_right": 5, "park_offical_id": "LINCO_11" }, "geometry": { "type": "Point", "coordinates": [ -0.535977914, 53.234990156 ] } }
]
}
