{
"type": "FeatureCollection",
"name": "DERDA_8_toilets",
"crs": { "type": "name", "properties": { "name": "urn:ogc:def:crs:OGC:1.3:CRS84" } },
"features": [
{ "type": "Feature", "properties": { "name": "Middleton Top Visitor Centre", "payment_info": "Free", "accessible": "True", "radar": "Unknown", "women": "True", "men": "True", "baby_change": "Unknown", "Mon": "Unknown", "Tue": "Unknown", "Wed": "Unknown", "Thu": "Unknown", "Fri": "Unknown", "Sat": "Unknown", "Sun": "Unknown", "index_right": 66, "park_offical_id": "DERDA_8" }, "geometry": { "type": "Point", "coordinates": [ -1.5902811, 53.0930356 ] } }
]
}
