{
"type": "FeatureCollection",
"name": "EREWA_45_toilets",
"crs": { "type": "name", "properties": { "name": "urn:ogc:def:crs:OGC:1.3:CRS84" } },
"features": [
{ "type": "Feature", "properties": { "name": "Long Eaton Train Station Wilsthorpe Road", "payment_info": "Free", "accessible": "False", "radar": "Unknown", "women": "True", "men": "True", "baby_change": "False", "Mon": "07:00-19:30", "Tue": "07:00-19:30", "Wed": "07:00-19:30", "Thu": "07:00-19:30", "Fri": "07:00-19:30", "Sat": "07:00-19:30", "Sun": "07:00-19:30", "index_right": 44, "park_offical_id": "EREWA_45" }, "geometry": { "type": "Point", "coordinates": [ -1.28626754, 52.885277296 ] } }
]
}
