{
"type": "FeatureCollection",
"name": "HARBO_84",
"crs": { "type": "name", "properties": { "name": "urn:ogc:def:crs:OGC:1.3:CRS84" } },
"features": [
{ "type": "Feature", "properties": { "osm_id": 7837521023, "name": null, "amenity": null, "man_made": null, "leisure": "picnic_table", "playground": null, "memorial": null }, "geometry": { "type": "Point", "coordinates": [ -1.2817366, 52.513853 ] } },
{ "type": "Feature", "properties": { "osm_id": 7837520996, "name": null, "amenity": null, "man_made": null, "leisure": "picnic_table", "playground": null, "memorial": null }, "geometry": { "type": "Point", "coordinates": [ -1.2811066, 52.5139286 ] } },
{ "type": "Feature", "properties": { "osm_id": 7837504318, "name": null, "amenity": null, "man_made": null, "leisure": "picnic_table", "playground": null, "memorial": null }, "geometry": { "type": "Point", "coordinates": [ -1.2814043, 52.5140799 ] } }
]
}
