{
"type": "FeatureCollection",
"name": "76b31d959afb_visibility",
"crs": { "type": "name", "properties": { "name": "urn:ogc:def:crs:OGC:1.3:CRS84" } },
"features": [
{ "type": "Feature", "properties": { "visible_points": 0, "total_points": 45, "visibility_pct": 0.0 }, "geometry": { "type": "Point", "coordinates": [ -0.637259062100539, 53.242531202270392 ] } },
{ "type": "Feature", "properties": { "visible_points": 4, "total_points": 50, "visibility_pct": 8.0 }, "geometry": { "type": "Point", "coordinates": [ -0.637051490314258, 53.242528829460838 ] } },
{ "type": "Feature", "properties": { "visible_points": 0, "total_points": 52, "visibility_pct": 0.0 }, "geometry": { "type": "Point", "coordinates": [ -0.63684391855739, 53.242526456289895 ] } },
{ "type": "Feature", "properties": { "visible_points": 0, "total_points": 52, "visibility_pct": 0.0 }, "geometry": { "type": "Point", "coordinates": [ -0.636636346829942, 53.242524082757605 ] } },
{ "type": "Feature", "properties": { "visible_points": 2, "total_points": 51, "visibility_pct": 3.9215686274509802 }, "geometry": { "type": "Point", "coordinates": [ -0.63642877513191, 53.24252170886394 ] } },
{ "type": "Feature", "properties": { "visible_points": 0, "total_points": 49, "visibility_pct": 0.0 }, "geometry": { "type": "Point", "coordinates": [ -0.637151853174156, 53.242637850283622 ] } },
{ "type": "Feature", "properties": { "visible_points": 4, "total_points": 52, "visibility_pct": 7.6923076923076925 }, "geometry": { "type": "Point", "coordinates": [ -0.636944280880883, 53.242635477283841 ] } },
{ "type": "Feature", "properties": { "visible_points": 3, "total_points": 52, "visibility_pct": 5.7692307692307692 }, "geometry": { "type": "Point", "coordinates": [ -0.636736708617028, 53.242633103922707 ] } },
{ "type": "Feature", "properties": { "visible_points": 4, "total_points": 52, "visibility_pct": 7.6923076923076925 }, "geometry": { "type": "Point", "coordinates": [ -0.63652913638259, 53.24263073020019 ] } },
{ "type": "Feature", "properties": { "visible_points": 5, "total_points": 51, "visibility_pct": 9.8039215686274517 }, "geometry": { "type": "Point", "coordinates": [ -0.636321564177576, 53.242628356116313 ] } },
{ "type": "Feature", "properties": { "visible_points": 0, "total_points": 45, "visibility_pct": 0.0 }, "geometry": { "type": "Point", "coordinates": [ -0.637252216541022, 53.242746871023478 ] } },
{ "type": "Feature", "properties": { "visible_points": 2, "total_points": 52, "visibility_pct": 3.8461538461538463 }, "geometry": { "type": "Point", "coordinates": [ -0.637044643711349, 53.242744498194867 ] } },
{ "type": "Feature", "properties": { "visible_points": 0, "total_points": 52, "visibility_pct": 0.0 }, "geometry": { "type": "Point", "coordinates": [ -0.636837070911085, 53.242742125004874 ] } },
{ "type": "Feature", "properties": { "visible_points": 3, "total_points": 52, "visibility_pct": 5.7692307692307692 }, "geometry": { "type": "Point", "coordinates": [ -0.636629498140237, 53.242739751453534 ] } },
{ "type": "Feature", "properties": { "visible_points": 1, "total_points": 52, "visibility_pct": 1.9230769230769231 }, "geometry": { "type": "Point", "coordinates": [ -0.636421925398809, 53.242737377540799 ] } },
{ "type": "Feature", "properties": { "visible_points": 5, "total_points": 47, "visibility_pct": 10.638297872340425 }, "geometry": { "type": "Point", "coordinates": [ -0.636214352686815, 53.242735003266716 ] } },
{ "type": "Feature", "properties": { "visible_points": 0, "total_points": 47, "visibility_pct": 0.0 }, "geometry": { "type": "Point", "coordinates": [ -0.637145007048789, 53.242853519022937 ] } },
{ "type": "Feature", "properties": { "visible_points": 0, "total_points": 52, "visibility_pct": 0.0 }, "geometry": { "type": "Point", "coordinates": [ -0.636937433712115, 53.242851146004114 ] } },
{ "type": "Feature", "properties": { "visible_points": 2, "total_points": 52, "visibility_pct": 3.8461538461538463 }, "geometry": { "type": "Point", "coordinates": [ -0.636729860404853, 53.242848772623923 ] } },
{ "type": "Feature", "properties": { "visible_points": 2, "total_points": 52, "visibility_pct": 3.8461538461538463 }, "geometry": { "type": "Point", "coordinates": [ -0.636522287127017, 53.242846398882371 ] } },
{ "type": "Feature", "properties": { "visible_points": 0, "total_points": 49, "visibility_pct": 0.0 }, "geometry": { "type": "Point", "coordinates": [ -0.636314713878601, 53.242844024779423 ] } },
{ "type": "Feature", "properties": { "visible_points": 0, "total_points": 42, "visibility_pct": 0.0 }, "geometry": { "type": "Point", "coordinates": [ -0.636107140659614, 53.2428416503151 ] } }
]
}
