{
"type": "FeatureCollection",
"name": "dfb4cbc8596d_visibility",
"crs": { "type": "name", "properties": { "name": "urn:ogc:def:crs:OGC:1.3:CRS84" } },
"features": [
{ "type": "Feature", "properties": { "visible_points": 1, "total_points": 46, "visibility_pct": 2.1739130434782608 }, "geometry": { "type": "Point", "coordinates": [ -1.1638063901835, 52.570207206467806 ] } },
{ "type": "Feature", "properties": { "visible_points": 2, "total_points": 48, "visibility_pct": 4.1666666666666661 }, "geometry": { "type": "Point", "coordinates": [ -1.163601972241281, 52.570205763744056 ] } },
{ "type": "Feature", "properties": { "visible_points": 4, "total_points": 49, "visibility_pct": 8.1632653061224492 }, "geometry": { "type": "Point", "coordinates": [ -1.163397554316948, 52.570204320667358 ] } },
{ "type": "Feature", "properties": { "visible_points": 3, "total_points": 48, "visibility_pct": 6.25 }, "geometry": { "type": "Point", "coordinates": [ -1.163193136410506, 52.570202877237733 ] } },
{ "type": "Feature", "properties": { "visible_points": 0, "total_points": 47, "visibility_pct": 0.0 }, "geometry": { "type": "Point", "coordinates": [ -1.162988718521963, 52.570201433455196 ] } },
{ "type": "Feature", "properties": { "visible_points": 0, "total_points": 52, "visibility_pct": 0.0 }, "geometry": { "type": "Point", "coordinates": [ -1.163702133652359, 52.570314350333248 ] } },
{ "type": "Feature", "properties": { "visible_points": 5, "total_points": 53, "visibility_pct": 9.433962264150944 }, "geometry": { "type": "Point", "coordinates": [ -1.163497715198573, 52.57031290742875 ] } },
{ "type": "Feature", "properties": { "visible_points": 6, "total_points": 53, "visibility_pct": 11.320754716981133 }, "geometry": { "type": "Point", "coordinates": [ -1.163293296762677, 52.570311464171319 ] } },
{ "type": "Feature", "properties": { "visible_points": 0, "total_points": 52, "visibility_pct": 0.0 }, "geometry": { "type": "Point", "coordinates": [ -1.163088878344677, 52.57031002056096 ] } },
{ "type": "Feature", "properties": { "visible_points": 0, "total_points": 53, "visibility_pct": 0.0 }, "geometry": { "type": "Point", "coordinates": [ -1.163597876591741, 52.570421494104203 ] } },
{ "type": "Feature", "properties": { "visible_points": 4, "total_points": 53, "visibility_pct": 7.5471698113207548 }, "geometry": { "type": "Point", "coordinates": [ -1.163393457626387, 52.570420051018935 ] } },
{ "type": "Feature", "properties": { "visible_points": 0, "total_points": 53, "visibility_pct": 0.0 }, "geometry": { "type": "Point", "coordinates": [ -1.16318903867893, 52.570418607580777 ] } },
{ "type": "Feature", "properties": { "visible_points": 1, "total_points": 53, "visibility_pct": 1.8867924528301887 }, "geometry": { "type": "Point", "coordinates": [ -1.163493619001647, 52.570528637780626 ] } },
{ "type": "Feature", "properties": { "visible_points": 6, "total_points": 53, "visibility_pct": 11.320754716981133 }, "geometry": { "type": "Point", "coordinates": [ -1.163289199524727, 52.570527194514632 ] } },
{ "type": "Feature", "properties": { "visible_points": 3, "total_points": 53, "visibility_pct": 5.6603773584905666 }, "geometry": { "type": "Point", "coordinates": [ -1.163389360882071, 52.570635781362533 ] } },
{ "type": "Feature", "properties": { "visible_points": 0, "total_points": 52, "visibility_pct": 0.0 }, "geometry": { "type": "Point", "coordinates": [ -1.163184940893579, 52.570634337915806 ] } },
{ "type": "Feature", "properties": { "visible_points": 0, "total_points": 47, "visibility_pct": 0.0 }, "geometry": { "type": "Point", "coordinates": [ -1.163489522750972, 52.570744368124501 ] } },
{ "type": "Feature", "properties": { "visible_points": 0, "total_points": 47, "visibility_pct": 0.0 }, "geometry": { "type": "Point", "coordinates": [ -1.163285102233011, 52.570742924849952 ] } },
{ "type": "Feature", "properties": { "visible_points": 4, "total_points": 41, "visibility_pct": 9.7560975609756095 }, "geometry": { "type": "Point", "coordinates": [ -1.163385264083995, 52.570851511698123 ] } },
{ "type": "Feature", "properties": { "visible_points": 4, "total_points": 40, "visibility_pct": 10.0 }, "geometry": { "type": "Point", "coordinates": [ -1.163180843054459, 52.570850068242827 ] } }
]
}
