{
"type": "FeatureCollection",
"name": "ASHFI_53_toilets",
"crs": { "type": "name", "properties": { "name": "urn:ogc:def:crs:OGC:1.3:CRS84" } },
"features": [
{ "type": "Feature", "properties": { "name": "Unknown", "payment_info": "Free", "accessible": "False", "radar": "Unknown", "women": "Unknown", "men": "Unknown", "baby_change": "Unknown", "Mon": "Unknown", "Tue": "Unknown", "Wed": "Unknown", "Thu": "Unknown", "Fri": "Unknown", "Sat": "Unknown", "Sun": "Unknown", "index_right": 66, "park_offical_id": "ASHFI_53" }, "geometry": { "type": "Point", "coordinates": [ -1.309038, 53.16633 ] } },
{ "type": "Feature", "properties": { "name": "Hardwick lakes", "payment_info": "Free", "accessible": "Unknown", "radar": "Unknown", "women": "True", "men": "True", "baby_change": "Unknown", "Mon": "Unknown", "Tue": "Unknown", "Wed": "Unknown", "Thu": "Unknown", "Fri": "Unknown", "Sat": "Unknown", "Sun": "Unknown", "index_right": 66, "park_offical_id": "ASHFI_53" }, "geometry": { "type": "Point", "coordinates": [ -1.323429858, 53.17106774 ] } },
{ "type": "Feature", "properties": { "name": "Unknown", "payment_info": "Free", "accessible": "False", "radar": "Unknown", "women": "Unknown", "men": "Unknown", "baby_change": "Unknown", "Mon": "Unknown", "Tue": "Unknown", "Wed": "Unknown", "Thu": "Unknown", "Fri": "Unknown", "Sat": "Unknown", "Sun": "Unknown", "index_right": 66, "park_offical_id": "ASHFI_53" }, "geometry": { "type": "Point", "coordinates": [ -1.3085678, 53.1691588 ] } }
]
}
