{
"type": "FeatureCollection",
"name": "e5da07bec8e7_visibility",
"crs": { "type": "name", "properties": { "name": "urn:ogc:def:crs:OGC:1.3:CRS84" } },
"features": [
{ "type": "Feature", "properties": { "visible_points": 0, "total_points": 48, "visibility_pct": 0.0 }, "geometry": { "type": "Point", "coordinates": [ -0.454778701910357, 53.238084683614666 ] } },
{ "type": "Feature", "properties": { "visible_points": 1, "total_points": 48, "visibility_pct": 2.083333333333333 }, "geometry": { "type": "Point", "coordinates": [ -0.454571165238978, 53.238081994330656 ] } },
{ "type": "Feature", "properties": { "visible_points": 1, "total_points": 47, "visibility_pct": 2.1276595744680851 }, "geometry": { "type": "Point", "coordinates": [ -0.454363628600917, 53.238079304685563 ] } },
{ "type": "Feature", "properties": { "visible_points": 0, "total_points": 48, "visibility_pct": 0.0 }, "geometry": { "type": "Point", "coordinates": [ -0.454878592393139, 53.238193857993174 ] } },
{ "type": "Feature", "properties": { "visible_points": 1, "total_points": 48, "visibility_pct": 2.083333333333333 }, "geometry": { "type": "Point", "coordinates": [ -0.454671055183817, 53.238191168876426 ] } },
{ "type": "Feature", "properties": { "visible_points": 0, "total_points": 48, "visibility_pct": 0.0 }, "geometry": { "type": "Point", "coordinates": [ -0.454463518007816, 53.238188479398559 ] } },
{ "type": "Feature", "properties": { "visible_points": 2, "total_points": 48, "visibility_pct": 4.1666666666666661 }, "geometry": { "type": "Point", "coordinates": [ -0.454255980865144, 53.238185789559573 ] } },
{ "type": "Feature", "properties": { "visible_points": 2, "total_points": 48, "visibility_pct": 4.1666666666666661 }, "geometry": { "type": "Point", "coordinates": [ -0.454770945633251, 53.238300343342956 ] } },
{ "type": "Feature", "properties": { "visible_points": 2, "total_points": 48, "visibility_pct": 4.1666666666666661 }, "geometry": { "type": "Point", "coordinates": [ -0.45456340791931, 53.238297654032337 ] } },
{ "type": "Feature", "properties": { "visible_points": 1, "total_points": 48, "visibility_pct": 2.083333333333333 }, "geometry": { "type": "Point", "coordinates": [ -0.454355870238685, 53.238294964360591 ] } },
{ "type": "Feature", "properties": { "visible_points": 0, "total_points": 48, "visibility_pct": 0.0 }, "geometry": { "type": "Point", "coordinates": [ -0.454870836587289, 53.238409517730283 ] } },
{ "type": "Feature", "properties": { "visible_points": 1, "total_points": 48, "visibility_pct": 2.083333333333333 }, "geometry": { "type": "Point", "coordinates": [ -0.454663298335397, 53.238406828586896 ] } },
{ "type": "Feature", "properties": { "visible_points": 1, "total_points": 48, "visibility_pct": 2.083333333333333 }, "geometry": { "type": "Point", "coordinates": [ -0.454455760116827, 53.238404139082377 ] } },
{ "type": "Feature", "properties": { "visible_points": 0, "total_points": 46, "visibility_pct": 0.0 }, "geometry": { "type": "Point", "coordinates": [ -0.454970728045931, 53.238518692038355 ] } },
{ "type": "Feature", "properties": { "visible_points": 0, "total_points": 48, "visibility_pct": 0.0 }, "geometry": { "type": "Point", "coordinates": [ -0.454763189256089, 53.238516003062216 ] } },
{ "type": "Feature", "properties": { "visible_points": 0, "total_points": 48, "visibility_pct": 0.0 }, "geometry": { "type": "Point", "coordinates": [ -0.454555650499565, 53.238513313724958 ] } },
{ "type": "Feature", "properties": { "visible_points": 1, "total_points": 47, "visibility_pct": 2.1276595744680851 }, "geometry": { "type": "Point", "coordinates": [ -0.454348111776368, 53.238510624026588 ] } },
{ "type": "Feature", "properties": { "visible_points": 3, "total_points": 42, "visibility_pct": 7.1428571428571423 }, "geometry": { "type": "Point", "coordinates": [ -0.454863080681383, 53.238625177458324 ] } },
{ "type": "Feature", "properties": { "visible_points": 3, "total_points": 43, "visibility_pct": 6.9767441860465116 }, "geometry": { "type": "Point", "coordinates": [ -0.454655541386912, 53.238622488288321 ] } },
{ "type": "Feature", "properties": { "visible_points": 0, "total_points": 43, "visibility_pct": 0.0 }, "geometry": { "type": "Point", "coordinates": [ -0.454448002125757, 53.238619798757171 ] } }
]
}
