{
"type": "FeatureCollection",
"name": "NORE5_27",
"crs": { "type": "name", "properties": { "name": "urn:ogc:def:crs:OGC:1.3:CRS84" } },
"features": [
{ "type": "Feature", "properties": { "osm_id": 9108340974, "name": null, "amenity": "bench", "man_made": null, "leisure": null, "playground": null, "memorial": null }, "geometry": { "type": "Point", "coordinates": [ -1.4619426, 53.3092802 ] } },
{ "type": "Feature", "properties": { "osm_id": 9108340976, "name": null, "amenity": "bench", "man_made": null, "leisure": null, "playground": null, "memorial": null }, "geometry": { "type": "Point", "coordinates": [ -1.4603099, 53.3095452 ] } },
{ "type": "Feature", "properties": { "osm_id": 9108340975, "name": null, "amenity": "bench", "man_made": null, "leisure": null, "playground": null, "memorial": null }, "geometry": { "type": "Point", "coordinates": [ -1.4603478, 53.3095452 ] } }
]
}
