{
"type": "FeatureCollection",
"name": "BROXT_56_toilets",
"crs": { "type": "name", "properties": { "name": "urn:ogc:def:crs:OGC:1.3:CRS84" } },
"features": [
{ "type": "Feature", "properties": { "name": "Weir Field Pavilion", "payment_info": "Free", "accessible": "True", "radar": "True", "women": "False", "men": "False", "baby_change": "False", "Mon": "Unknown", "Tue": "Unknown", "Wed": "Unknown", "Thu": "Unknown", "Fri": "Unknown", "Sat": "Unknown", "Sun": "Unknown", "index_right": 39, "park_offical_id": "BROXT_56" }, "geometry": { "type": "Point", "coordinates": [ -1.20384, 52.9127375 ] } }
]
}
