{
"type": "FeatureCollection",
"name": "LEICE_195_toilets",
"crs": { "type": "name", "properties": { "name": "urn:ogc:def:crs:OGC:1.3:CRS84" } },
"features": [
{ "type": "Feature", "properties": { "name": "Cossington Street", "payment_info": "Cost unknown", "accessible": "False", "radar": "Unknown", "women": "True", "men": "True", "baby_change": "False", "Mon": "07:00-20:00", "Tue": "07:00-20:00", "Wed": "07:00-20:00", "Thu": "07:00-20:00", "Fri": "07:00-20:00", "Sat": "07:00-20:00", "Sun": "07:00-20:00", "index_right": 75, "park_offical_id": "LEICE_195" }, "geometry": { "type": "Point", "coordinates": [ -1.120747429, 52.650936291 ] } },
{ "type": "Feature", "properties": { "name": "Belgrave Road", "payment_info": "Cost unknown", "accessible": "False", "radar": "Unknown", "women": "True", "men": "True", "baby_change": "False", "Mon": "07:00-20:00", "Tue": "07:00-20:00", "Wed": "07:00-20:00", "Thu": "07:00-20:00", "Fri": "07:00-20:00", "Sat": "07:00-20:00", "Sun": "07:00-20:00", "index_right": 75, "park_offical_id": "LEICE_195" }, "geometry": { "type": "Point", "coordinates": [ -1.123720653, 52.647874751 ] } }
]
}
