{
"type": "FeatureCollection",
"name": "LEICE_144_toilets",
"crs": { "type": "name", "properties": { "name": "urn:ogc:def:crs:OGC:1.3:CRS84" } },
"features": [
{ "type": "Feature", "properties": { "name": "Inside gp surgery on the left as you walk in", "payment_info": "Free", "accessible": "True", "radar": "True", "women": "True", "men": "True", "baby_change": "Unknown", "Mon": "Unknown", "Tue": "Unknown", "Wed": "Unknown", "Thu": "Unknown", "Fri": "Unknown", "Sat": "Unknown", "Sun": "Unknown", "index_right": 43, "park_offical_id": "LEICE_144" }, "geometry": { "type": "Point", "coordinates": [ -1.186666936, 52.630564351 ] } }
]
}
