{
"type": "FeatureCollection",
"name": "LEICE_162_toilets",
"crs": { "type": "name", "properties": { "name": "urn:ogc:def:crs:OGC:1.3:CRS84" } },
"features": [
{ "type": "Feature", "properties": { "name": "Westcotes Library", "payment_info": "Cost unknown", "accessible": "True", "radar": "Unknown", "women": "Unknown", "men": "Unknown", "baby_change": "Unknown", "Mon": "09:00-17:00", "Tue": "09:00-17:00", "Wed": "09:00-17:00", "Thu": "09:00-17:00", "Fri": "09:00-17:00", "Sat": "09:00-17:00", "Sun": "09:00-17:00", "index_right": 52, "park_offical_id": "LEICE_162" }, "geometry": { "type": "Point", "coordinates": [ -1.14810884, 52.629645839 ] } },
{ "type": "Feature", "properties": { "name": "SHELL NARBOROUGH ROAD", "payment_info": "Free", "accessible": "True", "radar": "False", "women": "True", "men": "True", "baby_change": "Unknown", "Mon": "09:00-17:00", "Tue": "09:00-17:00", "Wed": "09:00-17:00", "Thu": "09:00-17:00", "Fri": "09:00-17:00", "Sat": "09:00-17:00", "Sun": "09:00-17:00", "index_right": 52, "park_offical_id": "LEICE_162" }, "geometry": { "type": "Point", "coordinates": [ -1.152427197, 52.625425843 ] } },
{ "type": "Feature", "properties": { "name": "Tesco", "payment_info": "Cost unknown", "accessible": "True", "radar": "Unknown", "women": "True", "men": "True", "baby_change": "True", "Mon": "09:00-17:00", "Tue": "09:00-17:00", "Wed": "09:00-17:00", "Thu": "09:00-17:00", "Fri": "09:00-17:00", "Sat": "09:00-17:00", "Sun": "09:00-17:00", "index_right": 52, "park_offical_id": "LEICE_162" }, "geometry": { "type": "Point", "coordinates": [ -1.145721674, 52.632115455 ] } }
]
}
