{
"type": "FeatureCollection",
"name": "LEICE_183_toilets",
"crs": { "type": "name", "properties": { "name": "urn:ogc:def:crs:OGC:1.3:CRS84" } },
"features": [
{ "type": "Feature", "properties": { "name": "SHELL London Road", "payment_info": "Free", "accessible": "True", "radar": "False", "women": "True", "men": "True", "baby_change": "Unknown", "Mon": "09:00-17:00", "Tue": "09:00-17:00", "Wed": "09:00-17:00", "Thu": "09:00-17:00", "Fri": "09:00-17:00", "Sat": "Closed", "Sun": "Closed", "index_right": 69, "park_offical_id": "LEICE_183" }, "geometry": { "type": "Point", "coordinates": [ -1.095435619, 52.607007443 ] } },
{ "type": "Feature", "properties": { "name": "Knighton Park", "payment_info": "Free", "accessible": "False", "radar": "Unknown", "women": "True", "men": "True", "baby_change": "False", "Mon": "Unknown", "Tue": "Unknown", "Wed": "Unknown", "Thu": "Unknown", "Fri": "Unknown", "Sat": "Unknown", "Sun": "Unknown", "index_right": 69, "park_offical_id": "LEICE_183" }, "geometry": { "type": "Point", "coordinates": [ -1.104608774, 52.599584152 ] } }
]
}
