{
"type": "FeatureCollection",
"name": "RUSHC_351_toilets",
"crs": { "type": "name", "properties": { "name": "urn:ogc:def:crs:OGC:1.3:CRS84" } },
"features": [
{ "type": "Feature", "properties": { "name": "Ruddington Parish Council", "payment_info": "Cost unknown", "accessible": "False", "radar": "False", "women": "True", "men": "True", "baby_change": "Unknown", "Mon": "09:00-17:00", "Tue": "09:00-17:00", "Wed": "09:00-17:00", "Thu": "09:00-17:00", "Fri": "09:00-17:00", "Sat": "Closed", "Sun": "Closed", "index_right": 52, "park_offical_id": "RUSHC_351" }, "geometry": { "type": "Point", "coordinates": [ -1.150640845, 52.892087094 ] } },
{ "type": "Feature", "properties": { "name": "Rushcliffe Country Park", "payment_info": "Free", "accessible": "False", "radar": "Unknown", "women": "True", "men": "True", "baby_change": "Unknown", "Mon": "Unknown", "Tue": "Unknown", "Wed": "Unknown", "Thu": "Unknown", "Fri": "Unknown", "Sat": "Unknown", "Sun": "Unknown", "index_right": 52, "park_offical_id": "RUSHC_351" }, "geometry": { "type": "Point", "coordinates": [ -1.153151393, 52.884163539 ] } }
]
}
