{
"type": "FeatureCollection",
"name": "BLABY_14_toilets",
"crs": { "type": "name", "properties": { "name": "urn:ogc:def:crs:OGC:1.3:CRS84" } },
"features": [
{ "type": "Feature", "properties": { "name": "Motorway Services", "payment_info": "Free", "accessible": "False", "radar": "Unknown", "women": "True", "men": "True", "baby_change": "True", "Mon": "Unknown", "Tue": "Unknown", "Wed": "Unknown", "Thu": "Unknown", "Fri": "Unknown", "Sat": "Unknown", "Sun": "Unknown", "index_right": 11, "park_offical_id": "BLABY_14" }, "geometry": { "type": "Point", "coordinates": [ -1.2050816, 52.6193792 ] } },
{ "type": "Feature", "properties": { "name": "Motorway Services", "payment_info": "Free", "accessible": "False", "radar": "Unknown", "women": "True", "men": "True", "baby_change": "True", "Mon": "Unknown", "Tue": "Unknown", "Wed": "Unknown", "Thu": "Unknown", "Fri": "Unknown", "Sat": "Unknown", "Sun": "Unknown", "index_right": 11, "park_offical_id": "BLABY_14" }, "geometry": { "type": "Point", "coordinates": [ -1.2064713, 52.6190066 ] } }
]
}
