{
"type": "FeatureCollection",
"name": "BOLSO_47",
"crs": { "type": "name", "properties": { "name": "urn:ogc:def:crs:OGC:1.3:CRS84" } },
"features": [
{ "type": "Feature", "properties": { "osm_id": 708257476, "name": null, "amenity": "bench", "man_made": null, "leisure": null, "playground": null, "memorial": null }, "geometry": { "type": "Point", "coordinates": [ -1.2516293, 53.1822587 ] } },
{ "type": "Feature", "properties": { "osm_id": 708257477, "name": null, "amenity": "bench", "man_made": null, "leisure": null, "playground": null, "memorial": null }, "geometry": { "type": "Point", "coordinates": [ -1.2524233, 53.1827135 ] } },
{ "type": "Feature", "properties": { "osm_id": 708253438, "name": null, "amenity": "bench", "man_made": null, "leisure": null, "playground": null, "memorial": null }, "geometry": { "type": "Point", "coordinates": [ -1.2538904, 53.1819742 ] } },
{ "type": "Feature", "properties": { "osm_id": 708253437, "name": null, "amenity": "bench", "man_made": null, "leisure": null, "playground": null, "memorial": null }, "geometry": { "type": "Point", "coordinates": [ -1.2534184, 53.1821238 ] } }
]
}
