{
"type": "FeatureCollection",
"name": "RUSHC_31",
"crs": { "type": "name", "properties": { "name": "urn:ogc:def:crs:OGC:1.3:CRS84" } },
"features": [
{ "type": "Feature", "properties": { "osm_id": 7274687685, "name": null, "amenity": "bench", "man_made": null, "leisure": null, "playground": null, "memorial": null }, "geometry": { "type": "Point", "coordinates": [ -1.161705, 52.8928177 ] } },
{ "type": "Feature", "properties": { "osm_id": 7274687686, "name": null, "amenity": "bench", "man_made": null, "leisure": null, "playground": null, "memorial": null }, "geometry": { "type": "Point", "coordinates": [ -1.1617257, 52.8928367 ] } },
{ "type": "Feature", "properties": { "osm_id": 7274687687, "name": null, "amenity": "bench", "man_made": null, "leisure": null, "playground": null, "memorial": null }, "geometry": { "type": "Point", "coordinates": [ -1.1620832, 52.8929512 ] } }
]
}
