{
"type": "FeatureCollection",
"name": "WESNO_106",
"crs": { "type": "name", "properties": { "name": "urn:ogc:def:crs:OGC:1.3:CRS84" } },
"features": [
{ "type": "Feature", "properties": { "osm_id": 12705158079, "name": null, "amenity": null, "man_made": null, "leisure": "picnic_table", "playground": null, "memorial": null }, "geometry": { "type": "Point", "coordinates": [ -0.9697038, 52.2257037 ] } },
{ "type": "Feature", "properties": { "osm_id": 12705158078, "name": null, "amenity": null, "man_made": null, "leisure": "picnic_table", "playground": null, "memorial": null }, "geometry": { "type": "Point", "coordinates": [ -0.9698258, 52.2257167 ] } },
{ "type": "Feature", "properties": { "osm_id": 12705158077, "name": null, "amenity": null, "man_made": null, "leisure": "picnic_table", "playground": null, "memorial": null }, "geometry": { "type": "Point", "coordinates": [ -0.9698388, 52.2258362 ] } }
]
}
