{
"type": "FeatureCollection",
"name": "WESNO_23",
"crs": { "type": "name", "properties": { "name": "urn:ogc:def:crs:OGC:1.3:CRS84" } },
"features": [
{ "type": "Feature", "properties": { "osm_id": 12221964280, "name": null, "amenity": "bench", "man_made": null, "leisure": null, "playground": null, "memorial": null }, "geometry": { "type": "Point", "coordinates": [ -0.939625, 52.2315307 ] } },
{ "type": "Feature", "properties": { "osm_id": 12222087061, "name": null, "amenity": "bench", "man_made": null, "leisure": null, "playground": null, "memorial": null }, "geometry": { "type": "Point", "coordinates": [ -0.9393943, 52.2316113 ] } },
{ "type": "Feature", "properties": { "osm_id": 12222054937, "name": null, "amenity": "bench", "man_made": null, "leisure": null, "playground": null, "memorial": null }, "geometry": { "type": "Point", "coordinates": [ -0.9395777, 52.2316798 ] } }
]
}
