{
"type": "FeatureCollection",
"name": "e174f8623580_visibility",
"crs": { "type": "name", "properties": { "name": "urn:ogc:def:crs:OGC:1.3:CRS84" } },
"features": [
{ "type": "Feature", "properties": { "visible_points": 1, "total_points": 50, "visibility_pct": 2.0 }, "geometry": { "type": "Point", "coordinates": [ -1.196317600078909, 53.000109752152142 ] } },
{ "type": "Feature", "properties": { "visible_points": 0, "total_points": 49, "visibility_pct": 0.0 }, "geometry": { "type": "Point", "coordinates": [ -1.196111147269667, 53.000108357268893 ] } },
{ "type": "Feature", "properties": { "visible_points": 4, "total_points": 51, "visibility_pct": 7.8431372549019605 }, "geometry": { "type": "Point", "coordinates": [ -1.196625276318096, 53.00021970206469 ] } },
{ "type": "Feature", "properties": { "visible_points": 4, "total_points": 51, "visibility_pct": 7.8431372549019605 }, "geometry": { "type": "Point", "coordinates": [ -1.19641882298522, 53.000218307715272 ] } },
{ "type": "Feature", "properties": { "visible_points": 1, "total_points": 51, "visibility_pct": 1.9607843137254901 }, "geometry": { "type": "Point", "coordinates": [ -1.196212369669054, 53.000216913007421 ] } },
{ "type": "Feature", "properties": { "visible_points": 0, "total_points": 50, "visibility_pct": 0.0 }, "geometry": { "type": "Point", "coordinates": [ -1.1960059163696, 53.000215517941108 ] } },
{ "type": "Feature", "properties": { "visible_points": 1, "total_points": 51, "visibility_pct": 1.9607843137254901 }, "geometry": { "type": "Point", "coordinates": [ -1.196520046385829, 53.000326863135115 ] } },
{ "type": "Feature", "properties": { "visible_points": 2, "total_points": 51, "visibility_pct": 3.9215686274509802 }, "geometry": { "type": "Point", "coordinates": [ -1.196313592562807, 53.000325468605283 ] } },
{ "type": "Feature", "properties": { "visible_points": 4, "total_points": 51, "visibility_pct": 7.8431372549019605 }, "geometry": { "type": "Point", "coordinates": [ -1.196107138756465, 53.000324073716946 ] } },
{ "type": "Feature", "properties": { "visible_points": 0, "total_points": 50, "visibility_pct": 0.0 }, "geometry": { "type": "Point", "coordinates": [ -1.195900684966812, 53.000322678470106 ] } },
{ "type": "Feature", "properties": { "visible_points": 6, "total_points": 51, "visibility_pct": 11.76470588235294 }, "geometry": { "type": "Point", "coordinates": [ -1.196621270298072, 53.000435418330724 ] } },
{ "type": "Feature", "properties": { "visible_points": 4, "total_points": 51, "visibility_pct": 7.8431372549019605 }, "geometry": { "type": "Point", "coordinates": [ -1.196414815969651, 53.000434023981057 ] } },
{ "type": "Feature", "properties": { "visible_points": 2, "total_points": 51, "visibility_pct": 3.9215686274509802 }, "geometry": { "type": "Point", "coordinates": [ -1.196208361657886, 53.000432629272815 ] } },
{ "type": "Feature", "properties": { "visible_points": 1, "total_points": 51, "visibility_pct": 1.9607843137254901 }, "geometry": { "type": "Point", "coordinates": [ -1.19600190736278, 53.000431234206019 ] } },
{ "type": "Feature", "properties": { "visible_points": 0, "total_points": 50, "visibility_pct": 0.0 }, "geometry": { "type": "Point", "coordinates": [ -1.195795453084324, 53.000429838780661 ] } },
{ "type": "Feature", "properties": { "visible_points": 2, "total_points": 47, "visibility_pct": 4.2553191489361701 }, "geometry": { "type": "Point", "coordinates": [ -1.196722494706832, 53.000543973346893 ] } },
{ "type": "Feature", "properties": { "visible_points": 5, "total_points": 51, "visibility_pct": 9.8039215686274517 }, "geometry": { "type": "Point", "coordinates": [ -1.19651603987384, 53.000542579177001 ] } },
{ "type": "Feature", "properties": { "visible_points": 6, "total_points": 51, "visibility_pct": 11.76470588235294 }, "geometry": { "type": "Point", "coordinates": [ -1.196309585057497, 53.000541184648547 ] } },
{ "type": "Feature", "properties": { "visible_points": 0, "total_points": 51, "visibility_pct": 0.0 }, "geometry": { "type": "Point", "coordinates": [ -1.196103130257804, 53.000539789761518 ] } },
{ "type": "Feature", "properties": { "visible_points": 0, "total_points": 45, "visibility_pct": 0.0 }, "geometry": { "type": "Point", "coordinates": [ -1.196617264265948, 53.000651134280922 ] } },
{ "type": "Feature", "properties": { "visible_points": 4, "total_points": 48, "visibility_pct": 8.3333333333333321 }, "geometry": { "type": "Point", "coordinates": [ -1.196410808945026, 53.000649739932221 ] } }
]
}
