{
"type": "FeatureCollection",
"name": "NORNO_74",
"crs": { "type": "name", "properties": { "name": "urn:ogc:def:crs:OGC:1.3:CRS84" } },
"features": [
{ "type": "Feature", "properties": { "osm_id": 8176019832, "name": null, "amenity": null, "man_made": null, "leisure": "picnic_table", "playground": null, "memorial": null }, "geometry": { "type": "Point", "coordinates": [ -0.4745376, 52.473049 ] } },
{ "type": "Feature", "properties": { "osm_id": 8176019831, "name": null, "amenity": null, "man_made": null, "leisure": "picnic_table", "playground": null, "memorial": null }, "geometry": { "type": "Point", "coordinates": [ -0.474641, 52.4730496 ] } },
{ "type": "Feature", "properties": { "osm_id": 8176019830, "name": null, "amenity": null, "man_made": null, "leisure": "picnic_table", "playground": null, "memorial": null }, "geometry": { "type": "Point", "coordinates": [ -0.4746906, 52.4730902 ] } },
{ "type": "Feature", "properties": { "osm_id": 8176019829, "name": null, "amenity": null, "man_made": null, "leisure": "picnic_table", "playground": null, "memorial": null }, "geometry": { "type": "Point", "coordinates": [ -0.4747547, 52.4730684 ] } },
{ "type": "Feature", "properties": { "osm_id": 1577936174, "name": null, "amenity": null, "man_made": null, "leisure": "picnic_table", "playground": null, "memorial": null }, "geometry": { "type": "Point", "coordinates": [ -0.4750302, 52.4732824 ] } },
{ "type": "Feature", "properties": { "osm_id": 8176019872, "name": null, "amenity": null, "man_made": null, "leisure": "picnic_table", "playground": null, "memorial": null }, "geometry": { "type": "Point", "coordinates": [ -0.4782468, 52.4733643 ] } },
{ "type": "Feature", "properties": { "osm_id": 1577936112, "name": null, "amenity": null, "man_made": null, "leisure": "picnic_table", "playground": null, "memorial": null }, "geometry": { "type": "Point", "coordinates": [ -0.4747566, 52.4733738 ] } },
{ "type": "Feature", "properties": { "osm_id": 8176019818, "name": null, "amenity": null, "man_made": null, "leisure": "picnic_table", "playground": null, "memorial": null }, "geometry": { "type": "Point", "coordinates": [ -0.4757708, 52.4739166 ] } },
{ "type": "Feature", "properties": { "osm_id": 8175980692, "name": null, "amenity": null, "man_made": null, "leisure": "picnic_table", "playground": null, "memorial": null }, "geometry": { "type": "Point", "coordinates": [ -0.4753495, 52.4740816 ] } },
{ "type": "Feature", "properties": { "osm_id": 1577883648, "name": null, "amenity": null, "man_made": null, "leisure": "picnic_table", "playground": null, "memorial": null }, "geometry": { "type": "Point", "coordinates": [ -0.4772372, 52.474091 ] } },
{ "type": "Feature", "properties": { "osm_id": 8175980693, "name": null, "amenity": null, "man_made": null, "leisure": "picnic_table", "playground": null, "memorial": null }, "geometry": { "type": "Point", "coordinates": [ -0.4753082, 52.4741225 ] } },
{ "type": "Feature", "properties": { "osm_id": 8176019853, "name": null, "amenity": "bench", "man_made": null, "leisure": null, "playground": null, "memorial": null }, "geometry": { "type": "Point", "coordinates": [ -0.4801476, 52.4741262 ] } },
{ "type": "Feature", "properties": { "osm_id": 8175980694, "name": null, "amenity": null, "man_made": null, "leisure": "picnic_table", "playground": null, "memorial": null }, "geometry": { "type": "Point", "coordinates": [ -0.4753952, 52.4741284 ] } },
{ "type": "Feature", "properties": { "osm_id": 7924299859, "name": null, "amenity": null, "man_made": null, "leisure": "picnic_table", "playground": null, "memorial": null }, "geometry": { "type": "Point", "coordinates": [ -0.4756676, 52.4741926 ] } },
{ "type": "Feature", "properties": { "osm_id": 8176019826, "name": null, "amenity": "bench", "man_made": null, "leisure": null, "playground": null, "memorial": null }, "geometry": { "type": "Point", "coordinates": [ -0.4754855, 52.4741945 ] } },
{ "type": "Feature", "properties": { "osm_id": 7924299858, "name": null, "amenity": null, "man_made": null, "leisure": "picnic_table", "playground": null, "memorial": null }, "geometry": { "type": "Point", "coordinates": [ -0.4760595, 52.4742571 ] } }
]
}
