{
"type": "FeatureCollection",
"name": "NORNO_73",
"crs": { "type": "name", "properties": { "name": "urn:ogc:def:crs:OGC:1.3:CRS84" } },
"features": [
{ "type": "Feature", "properties": { "osm_id": 11898143758, "name": null, "amenity": "bench", "man_made": null, "leisure": null, "playground": null, "memorial": null }, "geometry": { "type": "Point", "coordinates": [ -0.7072861, 52.4877523 ] } },
{ "type": "Feature", "properties": { "osm_id": 11898143756, "name": null, "amenity": "bench", "man_made": null, "leisure": null, "playground": null, "memorial": null }, "geometry": { "type": "Point", "coordinates": [ -0.7065706, 52.4877564 ] } },
{ "type": "Feature", "properties": { "osm_id": 11898143755, "name": null, "amenity": "bench", "man_made": null, "leisure": null, "playground": null, "memorial": null }, "geometry": { "type": "Point", "coordinates": [ -0.708393, 52.4882593 ] } },
{ "type": "Feature", "properties": { "osm_id": 11898143761, "name": null, "amenity": "bench", "man_made": null, "leisure": null, "playground": null, "memorial": null }, "geometry": { "type": "Point", "coordinates": [ -0.7093021, 52.4891768 ] } },
{ "type": "Feature", "properties": { "osm_id": 11898143752, "name": null, "amenity": "bench", "man_made": null, "leisure": null, "playground": null, "memorial": null }, "geometry": { "type": "Point", "coordinates": [ -0.7096345, 52.4898217 ] } },
{ "type": "Feature", "properties": { "osm_id": 11898143760, "name": null, "amenity": null, "man_made": null, "leisure": "picnic_table", "playground": null, "memorial": null }, "geometry": { "type": "Point", "coordinates": [ -0.710181, 52.4902227 ] } },
{ "type": "Feature", "properties": { "osm_id": 11898143759, "name": null, "amenity": "bench", "man_made": null, "leisure": null, "playground": null, "memorial": null }, "geometry": { "type": "Point", "coordinates": [ -0.7097877, 52.4902626 ] } }
]
}
