{
"type": "FeatureCollection",
"name": "AMBVA_59_toilets",
"crs": { "type": "name", "properties": { "name": "urn:ogc:def:crs:OGC:1.3:CRS84" } },
"features": [
{ "type": "Feature", "properties": { "name": "Public Toilets Market Place", "payment_info": "Free", "accessible": "False", "radar": "Unknown", "women": "True", "men": "True", "baby_change": "Unknown", "Mon": "Unknown", "Tue": "Unknown", "Wed": "Unknown", "Thu": "Unknown", "Fri": "Unknown", "Sat": "Unknown", "Sun": "Unknown", "index_right": 63, "park_offical_id": "AMBVA_59" }, "geometry": { "type": "Point", "coordinates": [ -1.354000568, 53.013637546 ] } }
]
}
