{
"type": "FeatureCollection",
"name": "AMBVA_2_toilets",
"crs": { "type": "name", "properties": { "name": "urn:ogc:def:crs:OGC:1.3:CRS84" } },
"features": [
{ "type": "Feature", "properties": { "name": "Crossley park", "payment_info": "Free", "accessible": "True", "radar": "True", "women": "Unknown", "men": "Unknown", "baby_change": "False", "Mon": "Unknown", "Tue": "Unknown", "Wed": "Unknown", "Thu": "Unknown", "Fri": "Unknown", "Sat": "Unknown", "Sun": "Unknown", "index_right": 21, "park_offical_id": "AMBVA_2" }, "geometry": { "type": "Point", "coordinates": [ -1.4111628, 53.0497485 ] } },
{ "type": "Feature", "properties": { "name": "Ripley Town Hall", "payment_info": "Free", "accessible": "False", "radar": "Unknown", "women": "True", "men": "True", "baby_change": "Unknown", "Mon": "09:00-17:00", "Tue": "09:00-17:00", "Wed": "09:00-17:00", "Thu": "09:00-17:00", "Fri": "09:00-17:00", "Sat": "09:00-17:00", "Sun": "09:00-17:00", "index_right": 21, "park_offical_id": "AMBVA_2" }, "geometry": { "type": "Point", "coordinates": [ -1.407937109, 53.050554124 ] } }
]
}
