{
"type": "FeatureCollection",
"name": "AMBVA_25_toilets",
"crs": { "type": "name", "properties": { "name": "urn:ogc:def:crs:OGC:1.3:CRS84" } },
"features": [
{ "type": "Feature", "properties": { "name": "Appletree Medical Practice 47A Town Street", "payment_info": "Free", "accessible": "False", "radar": "Unknown", "women": "True", "men": "True", "baby_change": "Unknown", "Mon": "08:00-18:30", "Tue": "08:00-18:30", "Wed": "08:00-18:30", "Thu": "08:00-18:30", "Fri": "08:00-18:30", "Sat": "Closed", "Sun": "Closed", "index_right": 27, "park_offical_id": "AMBVA_25" }, "geometry": { "type": "Point", "coordinates": [ -1.4872112, 52.9853193 ] } }
]
}
