{
"type": "FeatureCollection",
"name": "BROXT_27",
"crs": { "type": "name", "properties": { "name": "urn:ogc:def:crs:OGC:1.3:CRS84" } },
"features": [
{ "type": "Feature", "properties": { "osm_id": 1701348109, "name": null, "amenity": "bench", "man_made": null, "leisure": null, "playground": null, "memorial": null }, "geometry": { "type": "Point", "coordinates": [ -1.2252561, 52.9806383 ] } },
{ "type": "Feature", "properties": { "osm_id": 1701348107, "name": null, "amenity": "bench", "man_made": null, "leisure": null, "playground": null, "memorial": null }, "geometry": { "type": "Point", "coordinates": [ -1.2215611, 52.983063 ] } },
{ "type": "Feature", "properties": { "osm_id": 1701348626, "name": null, "amenity": "bench", "man_made": null, "leisure": null, "playground": null, "memorial": null }, "geometry": { "type": "Point", "coordinates": [ -1.2217835, 52.9838696 ] } }
]
}
