{
"type": "FeatureCollection",
"name": "SOUKE_34",
"crs": { "type": "name", "properties": { "name": "urn:ogc:def:crs:OGC:1.3:CRS84" } },
"features": [
{ "type": "Feature", "properties": { "osm_id": 3439139622, "name": null, "amenity": "bench", "man_made": null, "leisure": null, "playground": null, "memorial": null }, "geometry": { "type": "Point", "coordinates": [ -0.3787967, 52.7588059 ] } },
{ "type": "Feature", "properties": { "osm_id": 10219274642, "name": null, "amenity": "bench", "man_made": null, "leisure": null, "playground": null, "memorial": null }, "geometry": { "type": "Point", "coordinates": [ -0.3743221, 52.7591701 ] } },
{ "type": "Feature", "properties": { "osm_id": 9559954348, "name": null, "amenity": "bench", "man_made": null, "leisure": null, "playground": null, "memorial": null }, "geometry": { "type": "Point", "coordinates": [ -0.3756541, 52.7605326 ] } },
{ "type": "Feature", "properties": { "osm_id": 9559954349, "name": null, "amenity": "bench", "man_made": null, "leisure": null, "playground": null, "memorial": null }, "geometry": { "type": "Point", "coordinates": [ -0.3754835, 52.7605741 ] } }
]
}
