{
"type": "FeatureCollection",
"name": "SOUKE_9",
"crs": { "type": "name", "properties": { "name": "urn:ogc:def:crs:OGC:1.3:CRS84" } },
"features": [
{ "type": "Feature", "properties": { "osm_id": 9062100783, "name": null, "amenity": null, "man_made": null, "leisure": "picnic_table", "playground": null, "memorial": null }, "geometry": { "type": "Point", "coordinates": [ -0.4794108, 52.6502474 ] } },
{ "type": "Feature", "properties": { "osm_id": 9062100786, "name": null, "amenity": "bench", "man_made": null, "leisure": null, "playground": null, "memorial": null }, "geometry": { "type": "Point", "coordinates": [ -0.4807366, 52.6502828 ] } },
{ "type": "Feature", "properties": { "osm_id": 9062100789, "name": null, "amenity": "bench", "man_made": null, "leisure": null, "playground": null, "memorial": null }, "geometry": { "type": "Point", "coordinates": [ -0.4792136, 52.6503373 ] } },
{ "type": "Feature", "properties": { "osm_id": 9062100790, "name": null, "amenity": "bench", "man_made": null, "leisure": null, "playground": null, "memorial": null }, "geometry": { "type": "Point", "coordinates": [ -0.4796968, 52.6504001 ] } },
{ "type": "Feature", "properties": { "osm_id": 9062100782, "name": null, "amenity": null, "man_made": null, "leisure": "picnic_table", "playground": null, "memorial": null }, "geometry": { "type": "Point", "coordinates": [ -0.4800351, 52.650417 ] } },
{ "type": "Feature", "properties": { "osm_id": 9062100781, "name": null, "amenity": null, "man_made": null, "leisure": "picnic_table", "playground": null, "memorial": null }, "geometry": { "type": "Point", "coordinates": [ -0.4803762, 52.6504404 ] } },
{ "type": "Feature", "properties": { "osm_id": 9062100780, "name": null, "amenity": null, "man_made": null, "leisure": "picnic_table", "playground": null, "memorial": null }, "geometry": { "type": "Point", "coordinates": [ -0.4806082, 52.6504506 ] } },
{ "type": "Feature", "properties": { "osm_id": 9062100788, "name": null, "amenity": null, "man_made": null, "leisure": "picnic_table", "playground": null, "memorial": null }, "geometry": { "type": "Point", "coordinates": [ -0.4803891, 52.6499362 ] } },
{ "type": "Feature", "properties": { "osm_id": 9062100784, "name": null, "amenity": "bench", "man_made": null, "leisure": null, "playground": null, "memorial": null }, "geometry": { "type": "Point", "coordinates": [ -0.4806323, 52.6499505 ] } },
{ "type": "Feature", "properties": { "osm_id": 9062100785, "name": null, "amenity": "bench", "man_made": null, "leisure": null, "playground": null, "memorial": null }, "geometry": { "type": "Point", "coordinates": [ -0.4807431, 52.6501315 ] } },
{ "type": "Feature", "properties": { "osm_id": 9062100787, "name": null, "amenity": null, "man_made": null, "leisure": "picnic_table", "playground": null, "memorial": null }, "geometry": { "type": "Point", "coordinates": [ -0.4806209, 52.6501625 ] } }
]
}
