{
"type": "FeatureCollection",
"name": "DERDA_55",
"crs": { "type": "name", "properties": { "name": "urn:ogc:def:crs:OGC:1.3:CRS84" } },
"features": [
{ "type": "Feature", "properties": { "osm_id": 11412760134, "name": null, "amenity": "bench", "man_made": null, "leisure": null, "playground": null, "memorial": null }, "geometry": { "type": "Point", "coordinates": [ -1.6407735, 53.26887 ] } },
{ "type": "Feature", "properties": { "osm_id": 13888774043, "name": null, "amenity": "bench", "man_made": null, "leisure": null, "playground": null, "memorial": null }, "geometry": { "type": "Point", "coordinates": [ -1.6411011, 53.2689134 ] } },
{ "type": "Feature", "properties": { "osm_id": 11412760132, "name": null, "amenity": "bench", "man_made": null, "leisure": null, "playground": null, "memorial": null }, "geometry": { "type": "Point", "coordinates": [ -1.6414086, 53.268996 ] } }
]
}
