{
"type": "FeatureCollection",
"name": "DERDA_0",
"crs": { "type": "name", "properties": { "name": "urn:ogc:def:crs:OGC:1.3:CRS84" } },
"features": [
{ "type": "Feature", "properties": { "osm_id": 13703835355, "name": null, "amenity": "bench", "man_made": null, "leisure": null, "playground": null, "memorial": null }, "geometry": { "type": "Point", "coordinates": [ -1.5598172, 53.117874 ] } },
{ "type": "Feature", "properties": { "osm_id": 13703835353, "name": null, "amenity": "bench", "man_made": null, "leisure": null, "playground": null, "memorial": null }, "geometry": { "type": "Point", "coordinates": [ -1.5598749, 53.1179392 ] } },
{ "type": "Feature", "properties": { "osm_id": 4036421318, "name": null, "amenity": "bench", "man_made": null, "leisure": null, "playground": null, "memorial": null }, "geometry": { "type": "Point", "coordinates": [ -1.5606101, 53.1186672 ] } },
{ "type": "Feature", "properties": { "osm_id": 13703835346, "name": null, "amenity": "bench", "man_made": null, "leisure": null, "playground": null, "memorial": null }, "geometry": { "type": "Point", "coordinates": [ -1.5613085, 53.1193252 ] } },
{ "type": "Feature", "properties": { "osm_id": 13703835345, "name": null, "amenity": "bench", "man_made": null, "leisure": null, "playground": null, "memorial": null }, "geometry": { "type": "Point", "coordinates": [ -1.562203, 53.1198894 ] } },
{ "type": "Feature", "properties": { "osm_id": 4036421335, "name": null, "amenity": null, "man_made": null, "leisure": "picnic_table", "playground": null, "memorial": null }, "geometry": { "type": "Point", "coordinates": [ -1.5625158, 53.1203824 ] } },
{ "type": "Feature", "properties": { "osm_id": 4036421336, "name": null, "amenity": null, "man_made": null, "leisure": "picnic_table", "playground": null, "memorial": null }, "geometry": { "type": "Point", "coordinates": [ -1.5624988, 53.1204373 ] } },
{ "type": "Feature", "properties": { "osm_id": 9044842004, "name": null, "amenity": "bench", "man_made": null, "leisure": null, "playground": null, "memorial": null }, "geometry": { "type": "Point", "coordinates": [ -1.5614533, 53.121227 ] } },
{ "type": "Feature", "properties": { "osm_id": 13703835338, "name": null, "amenity": "bench", "man_made": null, "leisure": null, "playground": null, "memorial": null }, "geometry": { "type": "Point", "coordinates": [ -1.5596643, 53.1213413 ] } }
]
}
