{
"type": "FeatureCollection",
"name": "13173f70eef8_visibility",
"crs": { "type": "name", "properties": { "name": "urn:ogc:def:crs:OGC:1.3:CRS84" } },
"features": [
{ "type": "Feature", "properties": { "visible_points": 1, "total_points": 44, "visibility_pct": 2.2727272727272729 }, "geometry": { "type": "Point", "coordinates": [ -0.176116968185563, 53.100350529812538 ] } },
{ "type": "Feature", "properties": { "visible_points": 7, "total_points": 50, "visibility_pct": 14.000000000000002 }, "geometry": { "type": "Point", "coordinates": [ -0.17591012712817, 53.100347362347883 ] } },
{ "type": "Feature", "properties": { "visible_points": 6, "total_points": 52, "visibility_pct": 11.538461538461538 }, "geometry": { "type": "Point", "coordinates": [ -0.175496445130581, 53.100341026340367 ] } },
{ "type": "Feature", "properties": { "visible_points": 0, "total_points": 52, "visibility_pct": 0.0 }, "geometry": { "type": "Point", "coordinates": [ -0.175289604190394, 53.100337857797527 ] } },
{ "type": "Feature", "properties": { "visible_points": 1, "total_points": 49, "visibility_pct": 2.0408163265306123 }, "geometry": { "type": "Point", "coordinates": [ -0.176008987357487, 53.100456761507019 ] } },
{ "type": "Feature", "properties": { "visible_points": 0, "total_points": 52, "visibility_pct": 0.0 }, "geometry": { "type": "Point", "coordinates": [ -0.175802145801969, 53.100453593851277 ] } },
{ "type": "Feature", "properties": { "visible_points": 0, "total_points": 52, "visibility_pct": 0.0 }, "geometry": { "type": "Point", "coordinates": [ -0.175595304285586, 53.100450425836115 ] } },
{ "type": "Feature", "properties": { "visible_points": 1, "total_points": 52, "visibility_pct": 1.9230769230769231 }, "geometry": { "type": "Point", "coordinates": [ -0.17538846280836, 53.100447257461511 ] } },
{ "type": "Feature", "properties": { "visible_points": 0, "total_points": 52, "visibility_pct": 0.0 }, "geometry": { "type": "Point", "coordinates": [ -0.175181621370281, 53.100444088727485 ] } },
{ "type": "Feature", "properties": { "visible_points": 4, "total_points": 52, "visibility_pct": 7.6923076923076925 }, "geometry": { "type": "Point", "coordinates": [ -0.175901005986822, 53.100562993109307 ] } },
{ "type": "Feature", "properties": { "visible_points": 0, "total_points": 52, "visibility_pct": 0.0 }, "geometry": { "type": "Point", "coordinates": [ -0.175694163932313, 53.100559825263474 ] } },
{ "type": "Feature", "properties": { "visible_points": 0, "total_points": 52, "visibility_pct": 0.0 }, "geometry": { "type": "Point", "coordinates": [ -0.175487321916946, 53.100556657058213 ] } },
{ "type": "Feature", "properties": { "visible_points": 1, "total_points": 52, "visibility_pct": 1.9230769230769231 }, "geometry": { "type": "Point", "coordinates": [ -0.175280479940731, 53.100553488493503 ] } },
{ "type": "Feature", "properties": { "visible_points": 2, "total_points": 49, "visibility_pct": 4.0816326530612246 }, "geometry": { "type": "Point", "coordinates": [ -0.175073638003674, 53.100550319569372 ] } },
{ "type": "Feature", "properties": { "visible_points": 4, "total_points": 52, "visibility_pct": 7.6923076923076925 }, "geometry": { "type": "Point", "coordinates": [ -0.175793024078011, 53.100669224609213 ] } },
{ "type": "Feature", "properties": { "visible_points": 0, "total_points": 52, "visibility_pct": 0.0 }, "geometry": { "type": "Point", "coordinates": [ -0.175586181524505, 53.100666056573289 ] } },
{ "type": "Feature", "properties": { "visible_points": 0, "total_points": 52, "visibility_pct": 0.0 }, "geometry": { "type": "Point", "coordinates": [ -0.175379339010153, 53.100662888177908 ] } },
{ "type": "Feature", "properties": { "visible_points": 4, "total_points": 49, "visibility_pct": 8.1632653061224492 }, "geometry": { "type": "Point", "coordinates": [ -0.175172496534956, 53.100659719423106 ] } },
{ "type": "Feature", "properties": { "visible_points": 5, "total_points": 51, "visibility_pct": 9.8039215686274517 }, "geometry": { "type": "Point", "coordinates": [ -0.175685041631044, 53.100775456006744 ] } },
{ "type": "Feature", "properties": { "visible_points": 0, "total_points": 51, "visibility_pct": 0.0 }, "geometry": { "type": "Point", "coordinates": [ -0.175478198578549, 53.100772287780707 ] } }
]
}
