{
"type": "FeatureCollection",
"name": "BASSE_27_toilets",
"crs": { "type": "name", "properties": { "name": "urn:ogc:def:crs:OGC:1.3:CRS84" } },
"features": [
{ "type": "Feature", "properties": { "name": "Chapelgate Car Park", "payment_info": "Free", "accessible": "True", "radar": "True", "women": "True", "men": "True", "baby_change": "True", "Mon": "09:00-17:00", "Tue": "09:00-17:00", "Wed": "09:00-17:00", "Thu": "09:00-17:00", "Fri": "09:00-17:00", "Sat": "09:00-17:00", "Sun": "09:00-17:00", "index_right": 44, "park_offical_id": "BASSE_27" }, "geometry": { "type": "Point", "coordinates": [ -0.941028595, 53.323687787 ] } }
]
}
