{
"type": "FeatureCollection",
"name": "SOUDE_62",
"crs": { "type": "name", "properties": { "name": "urn:ogc:def:crs:OGC:1.3:CRS84" } },
"features": [
{ "type": "Feature", "properties": { "osm_id": 4942472243, "name": null, "amenity": "bench", "man_made": null, "leisure": null, "playground": null, "memorial": null }, "geometry": { "type": "Point", "coordinates": [ -1.4509838, 52.8281819 ] } },
{ "type": "Feature", "properties": { "osm_id": 4942472244, "name": null, "amenity": "bench", "man_made": null, "leisure": null, "playground": null, "memorial": null }, "geometry": { "type": "Point", "coordinates": [ -1.4513622, 52.829197 ] } },
{ "type": "Feature", "properties": { "osm_id": 4942472248, "name": null, "amenity": "bench", "man_made": null, "leisure": null, "playground": null, "memorial": null }, "geometry": { "type": "Point", "coordinates": [ -1.4475154, 52.8325199 ] } }
]
}
