{
"type": "FeatureCollection",
"name": "SOUDE_21",
"crs": { "type": "name", "properties": { "name": "urn:ogc:def:crs:OGC:1.3:CRS84" } },
"features": [
{ "type": "Feature", "properties": { "osm_id": 404480250, "name": null, "amenity": "bench", "man_made": null, "leisure": null, "playground": null, "memorial": null }, "geometry": { "type": "Point", "coordinates": [ -1.4215859, 52.8197913 ] } },
{ "type": "Feature", "properties": { "osm_id": 404480307, "name": null, "amenity": "bench", "man_made": null, "leisure": null, "playground": null, "memorial": null }, "geometry": { "type": "Point", "coordinates": [ -1.4216429, 52.8198677 ] } }
]
}
