{
"type": "FeatureCollection",
"name": "9dc9e8f8f22b_visibility",
"crs": { "type": "name", "properties": { "name": "urn:ogc:def:crs:OGC:1.3:CRS84" } },
"features": [
{ "type": "Feature", "properties": { "visible_points": 1, "total_points": 38, "visibility_pct": 2.6315789473684208 }, "geometry": { "type": "Point", "coordinates": [ -1.556022055588141, 52.954081221869203 ] } },
{ "type": "Feature", "properties": { "visible_points": 0, "total_points": 43, "visibility_pct": 0.0 }, "geometry": { "type": "Point", "coordinates": [ -1.555815816879462, 52.954080451047162 ] } },
{ "type": "Feature", "properties": { "visible_points": 1, "total_points": 48, "visibility_pct": 2.083333333333333 }, "geometry": { "type": "Point", "coordinates": [ -1.555609578179887, 52.954079679867284 ] } },
{ "type": "Feature", "properties": { "visible_points": 0, "total_points": 49, "visibility_pct": 0.0 }, "geometry": { "type": "Point", "coordinates": [ -1.555711595165116, 52.954187933004398 ] } },
{ "type": "Feature", "properties": { "visible_points": 0, "total_points": 54, "visibility_pct": 0.0 }, "geometry": { "type": "Point", "coordinates": [ -1.555505355980326, 52.954187161639162 ] } },
{ "type": "Feature", "properties": { "visible_points": 0, "total_points": 53, "visibility_pct": 0.0 }, "geometry": { "type": "Point", "coordinates": [ -1.555607372956428, 52.954295414863729 ] } },
{ "type": "Feature", "properties": { "visible_points": 0, "total_points": 58, "visibility_pct": 0.0 }, "geometry": { "type": "Point", "coordinates": [ -1.555401133286428, 52.954294643313126 ] } },
{ "type": "Feature", "properties": { "visible_points": 0, "total_points": 59, "visibility_pct": 0.0 }, "geometry": { "type": "Point", "coordinates": [ -1.555194893625541, 52.954293871404722 ] } },
{ "type": "Feature", "properties": { "visible_points": 5, "total_points": 57, "visibility_pct": 8.7719298245614024 }, "geometry": { "type": "Point", "coordinates": [ -1.555503150253404, 52.954402896625147 ] } },
{ "type": "Feature", "properties": { "visible_points": 5, "total_points": 59, "visibility_pct": 8.4745762711864394 }, "geometry": { "type": "Point", "coordinates": [ -1.555296910098195, 52.954402124889207 ] } },
{ "type": "Feature", "properties": { "visible_points": 6, "total_points": 56, "visibility_pct": 10.714285714285714 }, "geometry": { "type": "Point", "coordinates": [ -1.555090669952087, 52.954401352795415 ] } },
{ "type": "Feature", "properties": { "visible_points": 5, "total_points": 52, "visibility_pct": 9.6153846153846168 }, "geometry": { "type": "Point", "coordinates": [ -1.554884429815103, 52.954400580343794 ] } },
{ "type": "Feature", "properties": { "visible_points": 5, "total_points": 46, "visibility_pct": 10.869565217391305 }, "geometry": { "type": "Point", "coordinates": [ -1.554678189687237, 52.954399807534351 ] } },
{ "type": "Feature", "properties": { "visible_points": 0, "total_points": 58, "visibility_pct": 0.0 }, "geometry": { "type": "Point", "coordinates": [ -1.55539892705604, 52.954510378288632 ] } },
{ "type": "Feature", "properties": { "visible_points": 3, "total_points": 55, "visibility_pct": 5.4545454545454541 }, "geometry": { "type": "Point", "coordinates": [ -1.555192686415605, 52.954509606367331 ] } },
{ "type": "Feature", "properties": { "visible_points": 3, "total_points": 51, "visibility_pct": 5.8823529411764701 }, "geometry": { "type": "Point", "coordinates": [ -1.554986445784292, 52.954508834088202 ] } },
{ "type": "Feature", "properties": { "visible_points": 3, "total_points": 47, "visibility_pct": 6.3829787234042552 }, "geometry": { "type": "Point", "coordinates": [ -1.554780205162095, 52.954508061451229 ] } },
{ "type": "Feature", "properties": { "visible_points": 0, "total_points": 41, "visibility_pct": 0.0 }, "geometry": { "type": "Point", "coordinates": [ -1.554573964549016, 52.954507288456419 ] } },
{ "type": "Feature", "properties": { "visible_points": 0, "total_points": 50, "visibility_pct": 0.0 }, "geometry": { "type": "Point", "coordinates": [ -1.555088462238677, 52.954617087747565 ] } },
{ "type": "Feature", "properties": { "visible_points": 0, "total_points": 46, "visibility_pct": 0.0 }, "geometry": { "type": "Point", "coordinates": [ -1.554882221122142, 52.954616315283076 ] } }
]
}
