{
"type": "FeatureCollection",
"name": "GEDLI_15",
"crs": { "type": "name", "properties": { "name": "urn:ogc:def:crs:OGC:1.3:CRS84" } },
"features": [
{ "type": "Feature", "properties": { "osm_id": 3733659827, "name": null, "amenity": "bench", "man_made": null, "leisure": null, "playground": null, "memorial": null }, "geometry": { "type": "Point", "coordinates": [ -1.0795913, 52.9690508 ] } },
{ "type": "Feature", "properties": { "osm_id": 3733659832, "name": null, "amenity": "bench", "man_made": null, "leisure": null, "playground": null, "memorial": null }, "geometry": { "type": "Point", "coordinates": [ -1.0795417, 52.9690625 ] } },
{ "type": "Feature", "properties": { "osm_id": 3733659841, "name": null, "amenity": "bench", "man_made": null, "leisure": null, "playground": null, "memorial": null }, "geometry": { "type": "Point", "coordinates": [ -1.0792219, 52.9691311 ] } }
]
}
