{
"type": "FeatureCollection",
"name": "GEDLI_48_toilets",
"crs": { "type": "name", "properties": { "name": "urn:ogc:def:crs:OGC:1.3:CRS84" } },
"features": [
{ "type": "Feature", "properties": { "name": "Colwick Country Park toilets", "payment_info": "Cost unknown", "accessible": "False", "radar": "False", "women": "False", "men": "False", "baby_change": "Unknown", "Mon": "Unknown", "Tue": "Unknown", "Wed": "Unknown", "Thu": "Unknown", "Fri": "Unknown", "Sat": "Unknown", "Sun": "Unknown", "index_right": 35, "park_offical_id": "GEDLI_48" }, "geometry": { "type": "Point", "coordinates": [ -1.090777293, 52.947826052 ] } }
]
}
