{
"type": "FeatureCollection",
"name": "0364db2d9d3d_visibility",
"crs": { "type": "name", "properties": { "name": "urn:ogc:def:crs:OGC:1.3:CRS84" } },
"features": [
{ "type": "Feature", "properties": { "visible_points": 3, "total_points": 50, "visibility_pct": 6.0 }, "geometry": { "type": "Point", "coordinates": [ -0.963094309196949, 53.063692687985984 ] } },
{ "type": "Feature", "properties": { "visible_points": 0, "total_points": 50, "visibility_pct": 0.0 }, "geometry": { "type": "Point", "coordinates": [ -0.962887571644183, 53.063690890412829 ] } },
{ "type": "Feature", "properties": { "visible_points": 1, "total_points": 50, "visibility_pct": 2.0 }, "geometry": { "type": "Point", "coordinates": [ -0.962680834113548, 53.063689092480494 ] } },
{ "type": "Feature", "properties": { "visible_points": 0, "total_points": 50, "visibility_pct": 0.0 }, "geometry": { "type": "Point", "coordinates": [ -0.962474096605027, 53.063687294188966 ] } },
{ "type": "Feature", "properties": { "visible_points": 0, "total_points": 50, "visibility_pct": 0.0 }, "geometry": { "type": "Point", "coordinates": [ -0.96319509046886, 53.063801438764756 ] } },
{ "type": "Feature", "properties": { "visible_points": 6, "total_points": 50, "visibility_pct": 12.0 }, "geometry": { "type": "Point", "coordinates": [ -0.962988352389898, 53.063799641364731 ] } },
{ "type": "Feature", "properties": { "visible_points": 7, "total_points": 50, "visibility_pct": 14.000000000000002 }, "geometry": { "type": "Point", "coordinates": [ -0.962781614333064, 53.063797843605492 ] } },
{ "type": "Feature", "properties": { "visible_points": 6, "total_points": 50, "visibility_pct": 12.0 }, "geometry": { "type": "Point", "coordinates": [ -0.962574876298347, 53.063796045487067 ] } },
{ "type": "Feature", "properties": { "visible_points": 3, "total_points": 50, "visibility_pct": 6.0 }, "geometry": { "type": "Point", "coordinates": [ -0.962368138285761, 53.063794247009461 ] } },
{ "type": "Feature", "properties": { "visible_points": 0, "total_points": 47, "visibility_pct": 0.0 }, "geometry": { "type": "Point", "coordinates": [ -0.963295872244826, 53.063910189458184 ] } },
{ "type": "Feature", "properties": { "visible_points": 4, "total_points": 50, "visibility_pct": 8.0 }, "geometry": { "type": "Point", "coordinates": [ -0.963089133639672, 53.063908392231262 ] } },
{ "type": "Feature", "properties": { "visible_points": 6, "total_points": 50, "visibility_pct": 12.0 }, "geometry": { "type": "Point", "coordinates": [ -0.962882395056638, 53.063906594645154 ] } },
{ "type": "Feature", "properties": { "visible_points": 6, "total_points": 50, "visibility_pct": 12.0 }, "geometry": { "type": "Point", "coordinates": [ -0.962675656495727, 53.063904796699831 ] } },
{ "type": "Feature", "properties": { "visible_points": 4, "total_points": 50, "visibility_pct": 8.0 }, "geometry": { "type": "Point", "coordinates": [ -0.962468917956936, 53.063902998395342 ] } },
{ "type": "Feature", "properties": { "visible_points": 2, "total_points": 46, "visibility_pct": 4.3478260869565215 }, "geometry": { "type": "Point", "coordinates": [ -0.962262179440281, 53.063901199731639 ] } },
{ "type": "Feature", "properties": { "visible_points": 0, "total_points": 50, "visibility_pct": 0.0 }, "geometry": { "type": "Point", "coordinates": [ -0.962983176284279, 53.064015345599451 ] } },
{ "type": "Feature", "properties": { "visible_points": 5, "total_points": 50, "visibility_pct": 10.0 }, "geometry": { "type": "Point", "coordinates": [ -0.962776437197161, 53.064013547827244 ] } },
{ "type": "Feature", "properties": { "visible_points": 4, "total_points": 50, "visibility_pct": 8.0 }, "geometry": { "type": "Point", "coordinates": [ -0.962569698132169, 53.064011749695851 ] } },
{ "type": "Feature", "properties": { "visible_points": 3, "total_points": 47, "visibility_pct": 6.3829787234042552 }, "geometry": { "type": "Point", "coordinates": [ -0.962362959089309, 53.064009951205271 ] } },
{ "type": "Feature", "properties": { "visible_points": 6, "total_points": 46, "visibility_pct": 13.043478260869565 }, "geometry": { "type": "Point", "coordinates": [ -0.962463739242394, 53.064118702593575 ] } }
]
}
