{
"type": "FeatureCollection",
"name": "SOUDE_68_toilets",
"crs": { "type": "name", "properties": { "name": "urn:ogc:def:crs:OGC:1.3:CRS84" } },
"features": [
{ "type": "Feature", "properties": { "name": "Melbourne Hall Visitor Centre", "payment_info": "Free", "accessible": "False", "radar": "False", "women": "True", "men": "True", "baby_change": "Unknown", "Mon": "Unknown", "Tue": "Unknown", "Wed": "Unknown", "Thu": "Unknown", "Fri": "Unknown", "Sat": "Unknown", "Sun": "Unknown", "index_right": 60, "park_offical_id": "SOUDE_68" }, "geometry": { "type": "Point", "coordinates": [ -1.422927976, 52.821520418 ] } },
{ "type": "Feature", "properties": { "name": "High Street", "payment_info": "Free", "accessible": "False", "radar": "False", "women": "True", "men": "True", "baby_change": "False", "Mon": "09:00-17:00", "Tue": "09:00-17:00", "Wed": "09:00-17:00", "Thu": "09:00-17:00", "Fri": "09:00-17:00", "Sat": "09:00-17:00", "Sun": "09:00-17:00", "index_right": 60, "park_offical_id": "SOUDE_68" }, "geometry": { "type": "Point", "coordinates": [ -1.430651292, 52.822339682 ] } }
]
}
