{
"type": "FeatureCollection",
"name": "98e3747fb39f_visibility",
"crs": { "type": "name", "properties": { "name": "urn:ogc:def:crs:OGC:1.3:CRS84" } },
"features": [
{ "type": "Feature", "properties": { "visible_points": 4, "total_points": 48, "visibility_pct": 8.3333333333333321 }, "geometry": { "type": "Point", "coordinates": [ -1.280242884287636, 52.952110371626553 ] } },
{ "type": "Feature", "properties": { "visible_points": 0, "total_points": 54, "visibility_pct": 0.0 }, "geometry": { "type": "Point", "coordinates": [ -1.280036664996708, 52.952109124050388 ] } },
{ "type": "Feature", "properties": { "visible_points": 0, "total_points": 48, "visibility_pct": 0.0 }, "geometry": { "type": "Point", "coordinates": [ -1.280344208381881, 52.95221885860515 ] } },
{ "type": "Feature", "properties": { "visible_points": 0, "total_points": 54, "visibility_pct": 0.0 }, "geometry": { "type": "Point", "coordinates": [ -1.280137988591552, 52.952217611200211 ] } },
{ "type": "Feature", "properties": { "visible_points": 7, "total_points": 59, "visibility_pct": 11.864406779661017 }, "geometry": { "type": "Point", "coordinates": [ -1.279931768816015, 52.952216363437536 ] } },
{ "type": "Feature", "properties": { "visible_points": 0, "total_points": 59, "visibility_pct": 0.0 }, "geometry": { "type": "Point", "coordinates": [ -1.279725549055271, 52.952215115317109 ] } },
{ "type": "Feature", "properties": { "visible_points": 2, "total_points": 59, "visibility_pct": 3.3898305084745761 }, "geometry": { "type": "Point", "coordinates": [ -1.279519329309335, 52.952213866838939 ] } },
{ "type": "Feature", "properties": { "visible_points": 3, "total_points": 59, "visibility_pct": 5.0847457627118651 }, "geometry": { "type": "Point", "coordinates": [ -1.280033092396041, 52.952324850674721 ] } },
{ "type": "Feature", "properties": { "visible_points": 7, "total_points": 59, "visibility_pct": 11.864406779661017 }, "geometry": { "type": "Point", "coordinates": [ -1.279826872135887, 52.952323602725507 ] } },
{ "type": "Feature", "properties": { "visible_points": 8, "total_points": 59, "visibility_pct": 13.559322033898304 }, "geometry": { "type": "Point", "coordinates": [ -1.279620651890527, 52.952322354418556 ] } },
{ "type": "Feature", "properties": { "visible_points": 6, "total_points": 55, "visibility_pct": 10.909090909090908 }, "geometry": { "type": "Point", "coordinates": [ -1.279414431659978, 52.952321105753832 ] } },
{ "type": "Feature", "properties": { "visible_points": 0, "total_points": 49, "visibility_pct": 0.0 }, "geometry": { "type": "Point", "coordinates": [ -1.279208211444235, 52.952319856731371 ] } },
{ "type": "Feature", "properties": { "visible_points": 0, "total_points": 57, "visibility_pct": 0.0 }, "geometry": { "type": "Point", "coordinates": [ -1.280134416460664, 52.952433337828083 ] } },
{ "type": "Feature", "properties": { "visible_points": 3, "total_points": 59, "visibility_pct": 5.0847457627118651 }, "geometry": { "type": "Point", "coordinates": [ -1.279928195701093, 52.952432090050095 ] } },
{ "type": "Feature", "properties": { "visible_points": 3, "total_points": 59, "visibility_pct": 5.0847457627118651 }, "geometry": { "type": "Point", "coordinates": [ -1.279721974956317, 52.952430841914335 ] } },
{ "type": "Feature", "properties": { "visible_points": 3, "total_points": 56, "visibility_pct": 5.3571428571428568 }, "geometry": { "type": "Point", "coordinates": [ -1.279515754226349, 52.952429593420831 ] } },
{ "type": "Feature", "properties": { "visible_points": 4, "total_points": 51, "visibility_pct": 7.8431372549019605 }, "geometry": { "type": "Point", "coordinates": [ -1.279309533511179, 52.952428344569569 ] } },
{ "type": "Feature", "properties": { "visible_points": 2, "total_points": 58, "visibility_pct": 3.4482758620689653 }, "geometry": { "type": "Point", "coordinates": [ -1.279823298506705, 52.952539329326299 ] } },
{ "type": "Feature", "properties": { "visible_points": 0, "total_points": 55, "visibility_pct": 0.0 }, "geometry": { "type": "Point", "coordinates": [ -1.279617077277308, 52.952538081004008 ] } },
{ "type": "Feature", "properties": { "visible_points": 0, "total_points": 50, "visibility_pct": 0.0 }, "geometry": { "type": "Point", "coordinates": [ -1.279410856062721, 52.952536832323965 ] } },
{ "type": "Feature", "properties": { "visible_points": 0, "total_points": 45, "visibility_pct": 0.0 }, "geometry": { "type": "Point", "coordinates": [ -1.279204634862937, 52.952535583286171 ] } },
{ "type": "Feature", "properties": { "visible_points": 0, "total_points": 49, "visibility_pct": 0.0 }, "geometry": { "type": "Point", "coordinates": [ -1.279512179098855, 52.952645319994502 ] } },
{ "type": "Feature", "properties": { "visible_points": 0, "total_points": 45, "visibility_pct": 0.0 }, "geometry": { "type": "Point", "coordinates": [ -1.279305957399646, 52.952644071127921 ] } }
]
}
