{
"type": "FeatureCollection",
"name": "5504f261915a_visibility",
"crs": { "type": "name", "properties": { "name": "urn:ogc:def:crs:OGC:1.3:CRS84" } },
"features": [
{ "type": "Feature", "properties": { "visible_points": 0, "total_points": 48, "visibility_pct": 0.0 }, "geometry": { "type": "Point", "coordinates": [ -0.438324806683515, 52.482862128149428 ] } },
{ "type": "Feature", "properties": { "visible_points": 0, "total_points": 49, "visibility_pct": 0.0 }, "geometry": { "type": "Point", "coordinates": [ -0.438120843160614, 52.482859436941219 ] } },
{ "type": "Feature", "properties": { "visible_points": 0, "total_points": 50, "visibility_pct": 0.0 }, "geometry": { "type": "Point", "coordinates": [ -0.437916879669993, 52.48285674538149 ] } },
{ "type": "Feature", "properties": { "visible_points": 0, "total_points": 51, "visibility_pct": 0.0 }, "geometry": { "type": "Point", "coordinates": [ -0.438422971228435, 52.482971314362651 ] } },
{ "type": "Feature", "properties": { "visible_points": 0, "total_points": 53, "visibility_pct": 0.0 }, "geometry": { "type": "Point", "coordinates": [ -0.438219007191221, 52.48296862331965 ] } },
{ "type": "Feature", "properties": { "visible_points": 0, "total_points": 54, "visibility_pct": 0.0 }, "geometry": { "type": "Point", "coordinates": [ -0.438015043186283, 52.482965931925122 ] } },
{ "type": "Feature", "properties": { "visible_points": 9, "total_points": 54, "visibility_pct": 16.666666666666664 }, "geometry": { "type": "Point", "coordinates": [ -0.437811079213621, 52.482963240179068 ] } },
{ "type": "Feature", "properties": { "visible_points": 0, "total_points": 54, "visibility_pct": 0.0 }, "geometry": { "type": "Point", "coordinates": [ -0.438317171703854, 52.483077809618592 ] } },
{ "type": "Feature", "properties": { "visible_points": 0, "total_points": 54, "visibility_pct": 0.0 }, "geometry": { "type": "Point", "coordinates": [ -0.438113207184598, 52.483075118389266 ] } },
{ "type": "Feature", "properties": { "visible_points": 0, "total_points": 54, "visibility_pct": 0.0 }, "geometry": { "type": "Point", "coordinates": [ -0.437909242697619, 52.483072426808391 ] } },
{ "type": "Feature", "properties": { "visible_points": 0, "total_points": 54, "visibility_pct": 0.0 }, "geometry": { "type": "Point", "coordinates": [ -0.438211371664944, 52.483184304773914 ] } },
{ "type": "Feature", "properties": { "visible_points": 0, "total_points": 54, "visibility_pct": 0.0 }, "geometry": { "type": "Point", "coordinates": [ -0.438007406663642, 52.483181613358262 ] } },
{ "type": "Feature", "properties": { "visible_points": 8, "total_points": 54, "visibility_pct": 14.814814814814813 }, "geometry": { "type": "Point", "coordinates": [ -0.437803441694617, 52.483178921591076 ] } },
{ "type": "Feature", "properties": { "visible_points": 0, "total_points": 54, "visibility_pct": 0.0 }, "geometry": { "type": "Point", "coordinates": [ -0.438105571111701, 52.48329079982863 ] } },
{ "type": "Feature", "properties": { "visible_points": 0, "total_points": 54, "visibility_pct": 0.0 }, "geometry": { "type": "Point", "coordinates": [ -0.437901605628343, 52.483288108226652 ] } },
{ "type": "Feature", "properties": { "visible_points": 8, "total_points": 52, "visibility_pct": 15.384615384615385 }, "geometry": { "type": "Point", "coordinates": [ -0.437697640177274, 52.483285416273134 ] } },
{ "type": "Feature", "properties": { "visible_points": 2, "total_points": 50, "visibility_pct": 4.0 }, "geometry": { "type": "Point", "coordinates": [ -0.438203736041786, 52.48339998621951 ] } },
{ "type": "Feature", "properties": { "visible_points": 0, "total_points": 50, "visibility_pct": 0.0 }, "geometry": { "type": "Point", "coordinates": [ -0.437999770044106, 52.483397294782719 ] } },
{ "type": "Feature", "properties": { "visible_points": 2, "total_points": 48, "visibility_pct": 4.1666666666666661 }, "geometry": { "type": "Point", "coordinates": [ -0.437795804078707, 52.483394602994409 ] } },
{ "type": "Feature", "properties": { "visible_points": 2, "total_points": 43, "visibility_pct": 4.6511627906976747 }, "geometry": { "type": "Point", "coordinates": [ -0.438097934941902, 52.483506481259305 ] } },
{ "type": "Feature", "properties": { "visible_points": 4, "total_points": 43, "visibility_pct": 9.3023255813953494 }, "geometry": { "type": "Point", "coordinates": [ -0.437893968462173, 52.483503789636202 ] } }
]
}
