{
"type": "FeatureCollection",
"name": "NOTTI_144_toilets",
"crs": { "type": "name", "properties": { "name": "urn:ogc:def:crs:OGC:1.3:CRS84" } },
"features": [
{ "type": "Feature", "properties": { "name": "Cafe toilet", "payment_info": "Free", "accessible": "Unknown", "radar": "Unknown", "women": "True", "men": "True", "baby_change": "Unknown", "Mon": "Unknown", "Tue": "Unknown", "Wed": "Unknown", "Thu": "Unknown", "Fri": "Unknown", "Sat": "Unknown", "Sun": "Unknown", "index_right": 36, "park_offical_id": "NOTTI_144" }, "geometry": { "type": "Point", "coordinates": [ -1.206136756, 53.015975613 ] } }
]
}
