{
"type": "FeatureCollection",
"name": "NOTTI_34_toilets",
"crs": { "type": "name", "properties": { "name": "urn:ogc:def:crs:OGC:1.3:CRS84" } },
"features": [
{ "type": "Feature", "properties": { "name": "Trent Vineyard Church ", "payment_info": "Free", "accessible": "True", "radar": "False", "women": "True", "men": "True", "baby_change": "True", "Mon": "09:00-18:00", "Tue": "09:00-18:00", "Wed": "09:00-18:00", "Thu": "09:00-18:00", "Fri": "09:00-18:00", "Sat": "Closed", "Sun": "08:00-20:30", "index_right": 116, "park_offical_id": "NOTTI_34" }, "geometry": { "type": "Point", "coordinates": [ -1.173123121, 52.942415462 ] } }
]
}
