{
"type": "FeatureCollection",
"name": "CHARN_70_toilets",
"crs": { "type": "name", "properties": { "name": "urn:ogc:def:crs:OGC:1.3:CRS84" } },
"features": [
{ "type": "Feature", "properties": { "name": "SHELL LOUGHBOROUGH", "payment_info": "Free", "accessible": "True", "radar": "Unknown", "women": "True", "men": "True", "baby_change": "Unknown", "Mon": "09:00-17:00", "Tue": "09:00-17:00", "Wed": "09:00-17:00", "Thu": "09:00-17:00", "Fri": "09:00-17:00", "Sat": "Closed", "Sun": "Closed", "index_right": 83, "park_offical_id": "CHARN_70" }, "geometry": { "type": "Point", "coordinates": [ -1.2120358, 52.7795278 ] } },
{ "type": "Feature", "properties": { "name": "Market Place", "payment_info": "020", "accessible": "False", "radar": "True", "women": "True", "men": "True", "baby_change": "True", "Mon": "Unknown", "Tue": "Unknown", "Wed": "Unknown", "Thu": "Unknown", "Fri": "Unknown", "Sat": "Unknown", "Sun": "Unknown", "index_right": 83, "park_offical_id": "CHARN_70" }, "geometry": { "type": "Point", "coordinates": [ -1.207058028, 52.771847134 ] } },
{ "type": "Feature", "properties": { "name": "Loughborough", "payment_info": "Free", "accessible": "False", "radar": "False", "women": "Unknown", "men": "Unknown", "baby_change": "False", "Mon": "Unknown", "Tue": "Unknown", "Wed": "Unknown", "Thu": "Unknown", "Fri": "Unknown", "Sat": "Unknown", "Sun": "Unknown", "index_right": 83, "park_offical_id": "CHARN_70" }, "geometry": { "type": "Point", "coordinates": [ -1.196200848, 52.779167832 ] } },
{ "type": "Feature", "properties": { "name": "Market Place Loughborough LE11 3EQ", "payment_info": "20p no change", "accessible": "True", "radar": "True", "women": "True", "men": "True", "baby_change": "True", "Mon": "09:00-17:00", "Tue": "09:00-17:00", "Wed": "09:00-17:00", "Thu": "08:30-17:30", "Fri": "09:00-17:00", "Sat": "08:30-17:30", "Sun": "09:00-16:30", "index_right": 83, "park_offical_id": "CHARN_70" }, "geometry": { "type": "Point", "coordinates": [ -1.2057559, 52.7714314 ] } }
]
}
