{
"type": "FeatureCollection",
"name": "84b5beced409_visibility",
"crs": { "type": "name", "properties": { "name": "urn:ogc:def:crs:OGC:1.3:CRS84" } },
"features": [
{ "type": "Feature", "properties": { "visible_points": 0, "total_points": 40, "visibility_pct": 0.0 }, "geometry": { "type": "Point", "coordinates": [ -0.006433194222858, 52.966902068337838 ] } },
{ "type": "Feature", "properties": { "visible_points": 0, "total_points": 47, "visibility_pct": 0.0 }, "geometry": { "type": "Point", "coordinates": [ -0.006531328488495, 52.967011605434323 ] } },
{ "type": "Feature", "properties": { "visible_points": 3, "total_points": 44, "visibility_pct": 6.8181818181818175 }, "geometry": { "type": "Point", "coordinates": [ -0.006325142032388, 52.967008149224881 ] } },
{ "type": "Feature", "properties": { "visible_points": 0, "total_points": 54, "visibility_pct": 0.0 }, "geometry": { "type": "Point", "coordinates": [ -0.00662946359714, 52.967121142204725 ] } },
{ "type": "Feature", "properties": { "visible_points": 0, "total_points": 51, "visibility_pct": 0.0 }, "geometry": { "type": "Point", "coordinates": [ -0.006423276604409, 52.967117686162453 ] } },
{ "type": "Feature", "properties": { "visible_points": 0, "total_points": 62, "visibility_pct": 0.0 }, "geometry": { "type": "Point", "coordinates": [ -0.006727599341864, 52.967230678725016 ] } },
{ "type": "Feature", "properties": { "visible_points": 0, "total_points": 58, "visibility_pct": 0.0 }, "geometry": { "type": "Point", "coordinates": [ -0.006521411824862, 52.967227222838638 ] } },
{ "type": "Feature", "properties": { "visible_points": 0, "total_points": 68, "visibility_pct": 0.0 }, "geometry": { "type": "Point", "coordinates": [ -0.006825735569094, 52.967340215175909 ] } },
{ "type": "Feature", "properties": { "visible_points": 0, "total_points": 66, "visibility_pct": 0.0 }, "geometry": { "type": "Point", "coordinates": [ -0.006619547527823, 52.967336759445438 ] } },
{ "type": "Feature", "properties": { "visible_points": 1, "total_points": 64, "visibility_pct": 1.5625 }, "geometry": { "type": "Point", "coordinates": [ -0.006923872278844, 52.96744975155741 ] } },
{ "type": "Feature", "properties": { "visible_points": 1, "total_points": 65, "visibility_pct": 1.5384615384615385 }, "geometry": { "type": "Point", "coordinates": [ -0.006717683713295, 52.967446295982846 ] } },
{ "type": "Feature", "properties": { "visible_points": 4, "total_points": 64, "visibility_pct": 6.25 }, "geometry": { "type": "Point", "coordinates": [ -0.006511495189488, 52.967442840051355 ] } },
{ "type": "Feature", "properties": { "visible_points": 0, "total_points": 55, "visibility_pct": 0.0 }, "geometry": { "type": "Point", "coordinates": [ -0.007228198602668, 52.967562742931236 ] } },
{ "type": "Feature", "properties": { "visible_points": 0, "total_points": 59, "visibility_pct": 0.0 }, "geometry": { "type": "Point", "coordinates": [ -0.007022009471108, 52.967559287869513 ] } },
{ "type": "Feature", "properties": { "visible_points": 0, "total_points": 61, "visibility_pct": 0.0 }, "geometry": { "type": "Point", "coordinates": [ -0.006815820381284, 52.967555832450842 ] } },
{ "type": "Feature", "properties": { "visible_points": 3, "total_points": 62, "visibility_pct": 4.838709677419355 }, "geometry": { "type": "Point", "coordinates": [ -0.006609631333201, 52.967552376675251 ] } },
{ "type": "Feature", "properties": { "visible_points": 1, "total_points": 49, "visibility_pct": 2.0408163265306123 }, "geometry": { "type": "Point", "coordinates": [ -0.007326336801733, 52.967672279018039 ] } },
{ "type": "Feature", "properties": { "visible_points": 0, "total_points": 53, "visibility_pct": 0.0 }, "geometry": { "type": "Point", "coordinates": [ -0.007120147145897, 52.967668824112188 ] } },
{ "type": "Feature", "properties": { "visible_points": 0, "total_points": 56, "visibility_pct": 0.0 }, "geometry": { "type": "Point", "coordinates": [ -0.006913957531796, 52.967665368849445 ] } },
{ "type": "Feature", "properties": { "visible_points": 4, "total_points": 57, "visibility_pct": 7.0175438596491224 }, "geometry": { "type": "Point", "coordinates": [ -0.006707767959428, 52.967661913229769 ] } },
{ "type": "Feature", "properties": { "visible_points": 0, "total_points": 47, "visibility_pct": 0.0 }, "geometry": { "type": "Point", "coordinates": [ -0.007218285303214, 52.967778360285486 ] } },
{ "type": "Feature", "properties": { "visible_points": 0, "total_points": 50, "visibility_pct": 0.0 }, "geometry": { "type": "Point", "coordinates": [ -0.00701209516483, 52.967774905178644 ] } },
{ "type": "Feature", "properties": { "visible_points": 4, "total_points": 52, "visibility_pct": 7.6923076923076925 }, "geometry": { "type": "Point", "coordinates": [ -0.006805905068183, 52.967771449714874 ] } },
{ "type": "Feature", "properties": { "visible_points": 4, "total_points": 46, "visibility_pct": 8.695652173913043 }, "geometry": { "type": "Point", "coordinates": [ -0.00690404265946, 52.967880986130581 ] } }
]
}
